{"@name": "DRAK_Cutlass_Black", "@group": null, "@type": "FlightController", "@subtype": "UNDEFINED", "@size": "1", "@Category": "Default", "ifcs": {"afterburn_accel_multiplier lateral": "2", "afterburn_accel_multiplier longitudinal": "2", "afterburn_accel_multiplier pitch": "1", "afterburn_accel_multiplier roll": "1", "afterburn_accel_multiplier transversal": "2", "afterburn_accel_multiplier yaw": "1", "angularTurbulenceAmplitude": "0.82", "angular_v_max pitch": "50", "angular_v_max roll": "95", "angular_v_max yaw": "45", "centerOfLiftOffset": "-2.5", "centerOfPressureOffset": "-3.5", "coefficientOfDrag": "1.62", "coefficientOfLift": "0.85", "linearTurbulenceAmplitude": "3", "maxAfterburnSpeed": "1114", "maxSpeed": "165", "scale back": "1", "scale down": "1", "scale forward": "1", "scale lateral": "1", "scale pitch_dn": "1", "scale pitch_up": "1", "scale roll_left": "0.75", "scale roll_right": "1", "scale up": "1", "scale yaw_left": "1", "scale yaw_right": "1", "thruster_count": 30, "thrusters": "hardpoint_Main_Retro_Left,hardpoint_Main_Retro_Right,hardpoint_Main_Thruster_Left,hardpoint_Main_Thruster_Right,hardpoint_Man_Thruster_Center_Bot,hardpoint_Man_Thruster_Center_Top,hardpoint_Man_Thruster_Left_Center,hardpoint_Man_Thruster_Left_Front,hardpoint_Man_Thruster_Left_Front_Bot,hardpoint_Man_Thruster_Left_Front_Top,hardpoint_Man_Thruster_Left_Outer_Bot,hardpoint_Man_Thruster_Left_Outer_Top,hardpoint_Man_Thruster_Left_Rear,hardpoint_Man_Thruster_Left_Rear_Bot,hardpoint_Man_Thruster_Left_Rear_Top,hardpoint_Man_Thruster_Left_Tail,hardpoint_Man_Thruster_Left_Wing_Bot,hardpoint_Man_Thruster_Left_Wing_Top,hardpoint_Man_Thruster_Right_Center,hardpoint_Man_Thruster_Right_Front,hardpoint_Man_Thruster_Right_Front_Bot,hardpoint_Man_Thruster_Right_Front_Top,hardpoint_Man_Thruster_Right_Outer_Bot,hardpoint_Man_Thruster_Right_Outer_Top,hardpoint_Man_Thruster_Right_Rear,hardpoint_Man_Thruster_Right_Rear_Bot,hardpoint_Man_Thruster_Right_Rear_Top,hardpoint_Man_Thruster_Right_Tail,hardpoint_Man_Thruster_Right_Wing_Bot,hardpoint_Man_Thruster_Right_Wing_Top", "torqueDistanceThreshold": "-1"}, "Components": {"SCItemFlightControllerParams": {"@PowerOffEffectTag": "00000000-0000-0000-0000-000000000000", "@PowerOnEffectTag": "00000000-0000-0000-0000-000000000000", "@__polymorphicType": "SCItemFlightControllerParams", "@__type": "DataForgeComponentParams", "@engineOffInteraction": "Interactable.SharedInteractions[1]", "@engineOnInteraction": "Interactable.SharedInteractions[0]", "@fuelWarningDisplayTime": "8", "@passiveRefuelWarningThresholdPercentage": "80"}, "SAttachableComponentParams": {"@__polymorphicType": "SAttachableComponentParams", "@__type": "DataForgeComponentParams", "AttachDef": {"@DisplayType": "", "@Grade": "1", "@Manufacturer": "00000000-0000-0000-0000-000000000000", "@RequiredTags": "", "@Size": "1", "@SubType": "UNDEFINED", "@Tags": "", "@Type": "FlightController", "@__type": "SItemDefinition", "Localization": {"@Description": "@LOC_EMPTY", "@Name": "@item_Name_FLGT_Controller", "@__type": "SCItemLocalization", "displayFeatures": {"@Callout1": "@LOC_EMPTY", "@Callout2": "@LOC_EMPTY", "@Callout3": "@LOC_EMPTY", "@FrontendBackground": "", "@History": "@LOC_EMPTY", "@LogoSimplifiedWhite": "", "@UIPriority": "0", "@__type": "SCExtendedLocalizationLevelParams"}}, "inventoryOccupancyVolume": {"SCentiCargoUnit": {"@__polymorphicType": "SCentiCargoUnit", "@__type": "SBaseCargoUnit", "@storagePoints": "0"}}, "mannequinTags": {"@__type": "SCItemMannequinTags", "@mannequinBaseTag": "", "@mannequinClassTag": "", "@mannequinTypeTag": ""}}}, "SCItem": {"@PlaceInteraction": "null", "@TurnOffInteraction": "null", "@TurnOnInteraction": "null", "@__polymorphicType": "SCItem", "@__type": "DataForgeComponentParams", "@attachToTileItemPort": "NoConnection", "@turnedOnByDefault": "0", "ItemPorts": null}, "SEntityInteractableParams": {"@__polymorphicType": "SEntityInteractableParams", "@__type": "DataForgeComponentParams", "Interactable": {"@__type": "SInteractableParams", "InteractionPoints": null, "SharedInteractions": {"SSharedInteractionParams": [{"@Name": "EngineOn", "@RoomTag": "00000000-0000-0000-0000-000000000000", "@UsableTag": "00000000-0000-0000-0000-000000000000", "@DisplayName": "@ui_interactor_engine_on", "@DisplayType": "Show", "@GenericCursor": "Button", "@FocusModeOnly": "0", "@Sendable": "0", "@Linkable": "1", "@LockedByLinks": "0", "@RequiresAuthorizedUser": "0", "@available": "1", "@__type": "SSharedInteractionParams", "QueryTags": null, "conditionList": null}, {"@Name": "EngineOff", "@RoomTag": "00000000-0000-0000-0000-000000000000", "@UsableTag": "00000000-0000-0000-0000-000000000000", "@DisplayName": "@ui_interactor_engine_off", "@DisplayType": "Show", "@GenericCursor": "Button", "@FocusModeOnly": "0", "@Sendable": "0", "@Linkable": "1", "@LockedByLinks": "0", "@RequiresAuthorizedUser": "0", "@available": "1", "@__type": "SSharedInteractionParams", "QueryTags": null, "conditionList": null}]}, "actionHandlerTasks": null, "interactionTasks": null}}, "SInteractionLinkParams": {"@__polymorphicType": "SInteractionLinkParams", "@__type": "DataForgeComponentParams", "linkPlugs": null, "vehicleItemPortInteractionLinks": null}}, "@BBoxSelection": "0", "@Icon": "", "@Invisible": "0", "@__path": "libs/foundry/records/entities/scitem/ships/controller/controller_flight_drak_cutlass_black.xml", "@__ref": "8b00b27b-32e2-446f-b6b4-4436f266bab5", "@__type": "EntityClassDefinition", "@lifetimePolicy": "00000000-0000-0000-0000-000000000000", "StaticEntityClassData": null, "tags": null, "Parts": {"Part": {"@name": "DRAK_Cutlass_Black", "@class": "Animated", "@mass": "226700.0", "@disablePhysics": "0", "@scopeContext": "Ship", "Animated": {"@filenameDestruction": "", "@damageMapFlag": "1", "@damageMapScale": "1.0, 1.0", "@damageMapOffset": "0.0,0.0"}, "Parts": {"Part": [{"@name": "hardpoint_armour", "@class": "ItemPort", "ItemPort": {"@minsize": "1", "@maxsize": "1", "@flags": "invisible uneditable", "Types": {"Type": {"@type": "Armor"}}}}, {"@name": "Body", "@class": "AnimatedJoint", "@damagemax": "7600", "@detachRatio": "0", "@detachBaseForce": "0,15,0", "@detachRandomForce": "0.5, 0.5, 0.5", "@detachRandomRotation": "0.5,0,0.3", "@detachProbability": "1", "@id": "modPart_body", "Effects": {"DetachFx": [{"@joint": "Body", "@effect": "Damage/LT_Damage/LT_Fire_FX.LT_Fire.lt_fire_16m_loop_fixed", "@pos_offset": "-0.0876228,-5.30445,-0.365069", "@rot_offset": "0.0,-0.999998,-0.00190687", "@helperID": "Body_PFX_DebrisFX_lt_fire_16m_loop_fixed008"}, {"@joint": "Body", "@effect": "Damage/LT_Damage/LT_Smoke_FX.LT_Smoke.lt_smoke_8m_linger_loop_trail", "@pos_offset": "-0.0876233,-4.51531,-0.365069", "@rot_offset": "0.0,-0.997392,0.0721727", "@helperID": "Body_PFX_DebrisFX_lt_smoke_8m_linger_loop_trail001"}, {"@joint": "Body", "@effect": "Damage/LT_Damage/LT_Explode_FX.LT_Explode.lt_explode_4m_once_fixed", "@pos_offset": "-0.0876228,-12.0774,-0.365069", "@rot_offset": "0.0,1.0,0.0", "@helperID": "Body_PFX_DebrisFX_lt_explode_4m_once_fixed"}]}, "DamageBehaviors": {"DamageBehavior": [{"@class": "DetachPart", "@damageRatioMin": "1", "DetachPart": {"Part": [{"@name": "Thruster_Main_Left", "@Probability": "0.3"}, {"@name": "Thruster_Main_Right", "@Probability": "0.3"}, {"@name": "Missile_Housing_Left", "@Probability": "0.2"}, {"@name": "Missile_Housing_Right", "@Probability": "0.2"}, {"@name": "Wing_Left", "@Probability": "0.5"}, {"@name": "Wing_Right", "@Probability": "0.5"}, {"@name": "Sidedoor_Left", "@Probability": "0.2"}, {"@name": "Sidedoor_Left_02", "@Probability": "0.2"}, {"@name": "Sidedoor_Right", "@Probability": "0.2"}, {"@name": "Sidedoor_Right_02", "@Probability": "0.2"}, {"@name": "Tail", "@Probability": "1"}, {"@name": "Body", "@Probability": "1"}]}}, {"@class": "Group", "@damageRatioMin": "1", "Group": {"@name": "Destroy"}}]}, "Parts": {"Part": [{"@name": "hardpoint_Man_Thruster_Center_Top", "@class": "ItemPort", "ItemPort": {"@minsize": "1", "@maxsize": "1", "@flags": "uneditable", "@display_name": "port_NameThrustManoeuv03", "Types": {"Type": {"@type": "ManneuverThruster", "@subtypes": ""}}, "Connections": {"Connection": [{"@pipeClass": "Power", "@pipe": "MainPower"}, {"@pipeClass": "Heat", "@pipe": "MainHeat"}, {"@pipeClass": "Fuel", "@pipe": "MainFuel"}]}}}, {"@name": "hardpoint_Man_Thruster_Center_Bot", "@class": "ItemPort", "ItemPort": {"@minsize": "1", "@maxsize": "1", "@flags": "uneditable", "@display_name": "port_NameThrustManoeuv03", "Types": {"Type": {"@type": "ManneuverThruster", "@subtypes": ""}}, "Connections": {"Connection": [{"@pipeClass": "Power", "@pipe": "MainPower"}, {"@pipeClass": "Heat", "@pipe": "MainHeat"}, {"@pipeClass": "Fuel", "@pipe": "MainFuel"}]}}}, {"@name": "hardpoint_Man_Thruster_Right_Center", "@class": "ItemPort", "ItemPort": {"@minsize": "1", "@maxsize": "1", "@flags": "uneditable", "@display_name": "port_NameThrustManoeuv03", "Types": {"Type": {"@type": "ManneuverThruster", "@subtypes": ""}}, "Connections": {"Connection": [{"@pipeClass": "Power", "@pipe": "MainPower"}, {"@pipeClass": "Heat", "@pipe": "MainHeat"}, {"@pipeClass": "Fuel", "@pipe": "MainFuel"}]}}}, {"@name": "hardpoint_Man_Thruster_Left_Center", "@class": "ItemPort", "ItemPort": {"@minsize": "1", "@maxsize": "1", "@flags": "uneditable", "@display_name": "port_NameThrustManoeuv03", "Types": {"Type": {"@type": "ManneuverThruster", "@subtypes": ""}}, "Connections": {"Connection": [{"@pipeClass": "Power", "@pipe": "MainPower"}, {"@pipeClass": "Heat", "@pipe": "MainHeat"}, {"@pipeClass": "Fuel", "@pipe": "MainFuel"}]}}}, {"@name": "hardpoint_Man_Thruster_Right_Front", "@class": "ItemPort", "ItemPort": {"@minsize": "1", "@maxsize": "1", "@flags": "uneditable", "@display_name": "port_NameThrustManoeuv03", "Types": {"Type": {"@type": "ManneuverThruster", "@subtypes": ""}}, "Connections": {"Connection": [{"@pipeClass": "Power", "@pipe": "MainPower"}, {"@pipeClass": "Heat", "@pipe": "MainHeat"}, {"@pipeClass": "Fuel", "@pipe": "MainFuel"}]}}}, {"@name": "hardpoint_Man_Thruster_Left_Front", "@class": "ItemPort", "ItemPort": {"@minsize": "1", "@maxsize": "1", "@flags": "uneditable", "@display_name": "port_NameThrustManoeuv03", "Types": {"Type": {"@type": "ManneuverThruster", "@subtypes": ""}}, "Connections": {"Connection": [{"@pipeClass": "Power", "@pipe": "MainPower"}, {"@pipeClass": "Heat", "@pipe": "MainHeat"}, {"@pipeClass": "Fuel", "@pipe": "MainFuel"}]}}}, {"@name": "hardpoint_Man_Thruster_Right_Rear", "@class": "ItemPort", "ItemPort": {"@minsize": "1", "@maxsize": "1", "@flags": "uneditable", "@display_name": "port_NameThrustManoeuv03", "Types": {"Type": {"@type": "ManneuverThruster", "@subtypes": ""}}, "Connections": {"Connection": [{"@pipeClass": "Power", "@pipe": "MainPower"}, {"@pipeClass": "Heat", "@pipe": "MainHeat"}, {"@pipeClass": "Fuel", "@pipe": "MainFuel"}]}}}, {"@name": "hardpoint_Man_Thruster_Left_Rear", "@class": "ItemPort", "ItemPort": {"@minsize": "1", "@maxsize": "1", "@flags": "uneditable", "@display_name": "port_NameThrustManoeuv03", "Types": {"Type": {"@type": "ManneuverThruster", "@subtypes": ""}}, "Connections": {"Connection": [{"@pipeClass": "Power", "@pipe": "MainPower"}, {"@pipeClass": "Heat", "@pipe": "MainHeat"}, {"@pipeClass": "Fuel", "@pipe": "MainFuel"}]}}}, {"@name": "Wing_Right", "@class": "AnimatedJoint", "@damageMax": "880", "@detachRatio": "1", "@detachBaseForce": "0,-10,0", "@detachRandomForce": "0.5, -0.5, 0.5", "@detachRandomRotation": "0.5,0,0.3", "@detachProbability": "1", "@id": "modPart_wingright", "Effects": {"DetachFx": [{"@joint": "Wing_Right", "@squibPhysical": "40", "@squibEnergy": "40", "@squibRadius": "1", "@pos_offset": "-2.86784,1.32483,1.04794", "@rot_offset": "0.0,1.0,0.0", "@helperID": "Wing_Right_SQUIB_1m001", "@effect": ""}, {"@joint": "Wing_Right", "@squibPhysical": "40", "@squibEnergy": "40", "@squibRadius": ".5", "@pos_offset": "-1.97046,-1.36315,1.04794", "@rot_offset": "0.0,1.0,0.0", "@helperID": "Wing_Right_SQUIB_.5m002", "@effect": ""}, {"@joint": "Wing_Right", "@squibPhysical": "40", "@squibEnergy": "40", "@squibRadius": ".5", "@pos_offset": "-2.86784,3.39267,1.04795", "@rot_offset": "0.0,1.0,0.0", "@helperID": "Wing_Right_SQUIB_.5m001", "@effect": ""}, {"@joint": "Wing_Right", "@partName": "Body", "@effect": "Damage/LT_Damage/LT_Fire_FX.LT_Fire.lt_fire_4m_loop_fixed", "@pos_offset": "-3.88503,1.60806,1.04853", "@rot_offset": "0.984808,-0.173648,0.0", "@helperID": "Wing_Right_PFX_DetachFX_lt_fire_4m_loop_fixed005"}, {"@joint": "Wing_Right", "@effect": "Damage/LT_Damage/LT_Fire_FX.LT_Fire.lt_fire_4m_loop_fixed", "@pos_offset": "-0.562348,1.19628,0.811815", "@rot_offset": "-0.984808,-0.173648,0.0", "@helperID": "Wing_Right_PFX_DebrisFX_lt_fire_4m_loop_fixed006"}, {"@joint": "Wing_Right", "@partName": "Body", "@effect": "Damage/LT_Damage/LT_Smoke_FX.LT_Smoke.lt_smoke_2m_loop_trail", "@pos_offset": "-3.6675,2.01965,0.989561", "@rot_offset": "0.984808,-0.173648,0.0", "@helperID": "Wing_Right_PFX_DetachFX_lt_smoke_2m_loop_trail001"}, {"@joint": "Wing_Right", "@effect": "Damage/LT_Damage/LT_Smoke_FX.LT_Smoke.lt_smoke_2m_loop_trail", "@pos_offset": "-1.9045,2.22262,0.989561", "@rot_offset": "-1.0,0.0,0.0", "@helperID": "Wing_Right_PFX_DebrisFX_lt_smoke_2m_loop_trail003"}, {"@joint": "Wing_Right", "@effect": "Damage/LT_Damage/LT_Smoke_FX.LT_Smoke.lt_smoke_4m_linger_loop_trail", "@pos_offset": "0.176213,1.23359,0.746554", "@rot_offset": "-0.984808,0.173648,0.0", "@helperID": "Wing_Right_PFX_DebrisFX_lt_smoke_4m_linger_loop_trail002"}, {"@joint": "Wing_Right", "@partName": "Body", "@effect": "Damage/LT_Damage/LT_Sparks_FX.LT_Sparks.lt_sparks_4m_once_fixed", "@pos_offset": "-2.87205,1.34107,0.989561", "@rot_offset": "0.984808,-0.173648,0.0", "@helperID": "Wing_Right_PFX_DetachFX_lt_sparks_4m_once_fixed001"}, {"@joint": "Wing_Right", "@effect": "Damage/LT_Damage/LT_Smoke_FX.LT_Smoke.lt_smoke_2m_loop_trail", "@pos_offset": "-1.20047,-0.495635,0.98956", "@rot_offset": "-0.906308,0.422618,0.0", "@helperID": "Wing_Right_PFX_DebrisFX_lt_smoke_2m_loop_trail004"}, {"@joint": "Wing_Right", "@partName": "Body", "@effect": "Damage/LT_Damage/LT_Sparks_FX.LT_Sparks.lt_sparks_2m_loop_fixed", "@pos_offset": "-2.68395,1.54904,1.43497", "@rot_offset": "0.642787,0.766045,0.0", "@helperID": "Wing_Right_PFX_DetachFX_lt_sparks_2m_loop_fixed001"}, {"@joint": "Wing_Right", "@partName": "Body", "@effect": "Damage/LT_Damage/LT_Sparks_FX.LT_Sparks.lt_sparks_1m_loop_fixed", "@pos_offset": "-2.98621,3.12838,0.667197", "@rot_offset": "0.453154,0.026445,-0.89104", "@helperID": "Wing_Right_PFX_DetachFX_lt_sparks_1m_loop_fixed001"}, {"@joint": "Wing_Right", "@partName": "Body", "@effect": "Damage/LT_Damage/LT_Smoke_FX.LT_Smoke.lt_smoke_1m_loop_trail", "@pos_offset": "-3.12939,1.81322,0.416567", "@rot_offset": "0.730579,0.0264449,-0.682316", "@helperID": "Wing_Right_PFX_DetachFX_lt_smoke_1m_loop_trail001"}, {"@joint": "Wing_Right", "@partName": "Body", "@effect": "Damage/LT_Damage/LT_Smoke_FX.LT_Smoke.lt_smoke_1m_loop_trail", "@pos_offset": "-3.71908,2.77282,0.234744", "@rot_offset": "0.730579,0.0264449,-0.682316", "@helperID": "Wing_Right_PFX_DetachFX_lt_smoke_1m_loop_trail002"}, {"@joint": "Wing_Right", "@partName": "Body", "@effect": "Damage/LT_Damage/LT_Fire_FX.LT_Fire.lt_fire_50cm_loop_fixed", "@pos_offset": "-2.68395,1.54904,1.43497", "@rot_offset": "0.642787,0.766045,0.0", "@helperID": "Wing_Right_PFX_DetachFX_lt_fire_50cm_loop_fixed001"}, {"@joint": "Wing_Right", "@partName": "Body", "@effect": "Damage/LT_Damage/LT_Fire_FX.LT_Fire.lt_fire_50cm_loop_fixed", "@pos_offset": "-3.71908,2.77282,0.234744", "@rot_offset": "0.730579,0.0264449,-0.682316", "@helperID": "Wing_Right_PFX_DetachFX_lt_fire_50cm_loop_fixed002"}, {"@joint": "Wing_Right", "@partName": "Body", "@effect": "Damage/LT_Damage/LT_Fire_FX.LT_Fire.lt_fire_1m_loop_fixed", "@pos_offset": "-2.82389,-0.483987,1.0597", "@rot_offset": "0.918973,-0.39325,0.0290163", "@helperID": "Wing_Right_PFX_DetachFX_lt_fire_1m_loop_fixed005"}, {"@joint": "Wing_Right", "@partName": "Body", "@effect": "Damage/LT_Damage/LT_Smoke_FX.LT_Smoke.lt_smoke_2m_loop_trail", "@pos_offset": "-2.66024,-0.248097,0.98956", "@rot_offset": "0.984808,-0.173648,0.0", "@helperID": "Wing_Right_PFX_DetachFX_lt_smoke_2m_loop_trail003"}, {"@joint": "Wing_Right", "@partName": "Body", "@effect": "Damage/LT_Damage/LT_Explode_FX.LT_Explode.lt_explode_2m_once_fixed", "@pos_offset": "-2.68395,1.54904,1.43497", "@rot_offset": "0.642787,0.766045,0.0", "@helperID": "Wing_Right_PFX_DetachFX_lt_explode_2m_once_fixed002"}]}, "Parts": {"Part": [{"@name": "hardpoint_Man_Thruster_Right_Outer_Bot", "@class": "ItemPort", "ItemPort": {"@minsize": "1", "@maxsize": "1", "@flags": "uneditable", "@display_name": "port_NameThrustManoeuv03", "Types": {"Type": {"@type": "ManneuverThruster", "@subtypes": ""}}, "Connections": {"Connection": [{"@pipeClass": "Power", "@pipe": "MainPower"}, {"@pipeClass": "Heat", "@pipe": "MainHeat"}, {"@pipeClass": "Fuel", "@pipe": "MainFuel"}]}}}, {"@name": "hardpoint_Man_Thruster_Right_Outer_Top", "@class": "ItemPort", "ItemPort": {"@minsize": "1", "@maxsize": "1", "@flags": "uneditable", "@display_name": "port_NameThrustManoeuv03", "Types": {"Type": {"@type": "ManneuverThruster", "@subtypes": ""}}, "Connections": {"Connection": [{"@pipeClass": "Power", "@pipe": "MainPower"}, {"@pipeClass": "Heat", "@pipe": "MainHeat"}, {"@pipeClass": "Fuel", "@pipe": "MainFuel"}]}}}, {"@name": "hardpoint_Man_Thruster_Right_Wing_Bot", "@class": "ItemPort", "ItemPort": {"@minsize": "1", "@maxsize": "1", "@flags": "uneditable", "@display_name": "port_NameThrustManoeuv03", "Types": {"Type": {"@type": "ManneuverThruster", "@subtypes": ""}}, "Connections": {"Connection": [{"@pipeClass": "Power", "@pipe": "MainPower"}, {"@pipeClass": "Heat", "@pipe": "MainHeat"}, {"@pipeClass": "Fuel", "@pipe": "MainFuel"}]}}}, {"@name": "hardpoint_Man_Thruster_Right_Wing_Top", "@class": "ItemPort", "ItemPort": {"@minsize": "1", "@maxsize": "1", "@flags": "uneditable", "@display_name": "port_NameThrustManoeuv03", "Types": {"Type": {"@type": "ManneuverThruster", "@subtypes": ""}}, "Connections": {"Connection": [{"@pipeClass": "Power", "@pipe": "MainPower"}, {"@pipeClass": "Heat", "@pipe": "MainHeat"}, {"@pipeClass": "Fuel", "@pipe": "MainFuel"}]}}}, {"@name": "hardpoint_Right_Wing_Utility", "@class": "ItemPort", "ItemPort": {"@minsize": "1", "@maxsize": "1", "@flags": "uneditable", "@display_name": "port_NameWeaponSlot02", "Pitch": {"@min": "-30", "@max": "5"}, "Yaw": {"@min": "-15", "@max": "15"}, "Connections": {"Connection": [{"@pipeClass": "Power", "@pipe": "MainPower"}, {"@pipeClass": "Heat", "@pipe": "MainHeat"}]}}}, {"@name": "hardpoint_Right_Wing_Weapon", "@class": "ItemPort", "ItemPort": {"@minsize": "3", "@maxsize": "3", "@flags": "", "@display_name": "port_NameWeaponSlot02", "@defaultWeaponGroup": "1", "Types": {"Type": [{"@type": "Turret", "@subtypes": "GunTurret"}, {"@type": "WeaponGun", "@subtypes": "Gun"}]}, "Pitch": {"@min": "-30", "@max": "5"}, "Yaw": {"@min": "-15", "@max": "15"}, "Connections": {"Connection": [{"@pipeClass": "Power", "@pipe": "MainPower"}, {"@pipeClass": "Heat", "@pipe": "MainHeat"}]}}}]}}, {"@name": "hardpoint_cooler_left", "@class": "ItemPort", "ItemPort": {"@minsize": "2", "@maxsize": "2", "@flags": "invisible", "Types": {"Type": {"@type": "Cooler", "@subtypes": ""}}, "Connections": {"Connection": [{"@pipeClass": "Power", "@pipe": "MainPower"}, {"@pipeClass": "Heat", "@pipe": "MainHeat"}]}}}, {"@name": "hardpoint_power_plant", "@class": "ItemPort", "ItemPort": {"@minsize": "2", "@maxsize": "2", "@flags": "invisible", "@display_name": "port_NamePowerplant01", "Types": {"Type": {"@type": "PowerPlant", "@subtypes": ""}}, "Connections": {"Connection": [{"@pipeClass": "Power", "@pipe": "MainPower"}, {"@pipeClass": "Heat", "@pipe": "MainHeat"}]}}}, {"@name": "hardpoint_fuel_intake_right", "@class": "ItemPort", "ItemPort": {"@minsize": "1", "@maxsize": "1", "@flags": "invisible uneditable", "Types": {"Type": {"@type": "FuelIntake"}}, "Connections": {"Connection": [{"@pipeClass": "Power", "@pipe": "MainPower"}, {"@pipeClass": "Heat", "@pipe": "MainHeat"}, {"@pipeClass": "Fuel", "@pipe": "IntakeFuel"}]}}}, {"@name": "hardpoint_fuel_tank_left", "@class": "ItemPort", "ItemPort": {"@minsize": "1", "@maxsize": "1", "@flags": "invisible uneditable", "Types": {"Type": {"@type": "FuelTank"}}, "Connections": {"Connection": [{"@pipeClass": "Input", "@pipe": "IntakeFuel"}, {"@pipeClass": "Output", "@pipe": "MainFuel"}]}}}, {"@name": "hardpoint_fuel_tank_right", "@class": "ItemPort", "ItemPort": {"@minsize": "1", "@maxsize": "1", "@flags": "invisible uneditable", "Types": {"Type": {"@type": "FuelTank"}}, "Connections": {"Connection": [{"@pipeClass": "Input", "@pipe": "IntakeFuel"}, {"@pipeClass": "Output", "@pipe": "MainFuel"}]}}}, {"@name": "hardpoint_life_support", "@class": "ItemPort", "ItemPort": {"@minsize": "1", "@maxsize": "1", "@flags": "uneditable", "@display_name": "port_NameLifesupp", "Types": {"Type": {"@type": "LifeSupport", "@subtypes": ""}}, "Connections": {"Connection": [{"@pipeClass": "Power", "@pipe": "MainPower"}, {"@pipeClass": "Heat", "@pipe": "MainHeat"}]}}}, {"@name": "hardpoint_cockpit_selfdestruct", "@class": "ItemPort", "ItemPort": {"@minsize": "1", "@maxsize": "1", "@flags": "invisible uneditable", "@display_name": "Self Destruct", "Types": {"Type": {"@type": "SelfDestruct"}}, "Connections": {"Connection": {"@pipeClass": "Power", "@pipe": "MainPower"}}}}, {"@name": "hardpoint_quantum_drive", "@class": "ItemPort", "ItemPort": {"@minsize": "2", "@maxsize": "2", "@flags": "invisible", "Types": {"Type": {"@type": "QuantumDrive", "@subtypes": "QDrive"}}, "Connections": {"Connection": [{"@pipeClass": "Power", "@pipe": "MainPower"}, {"@pipeClass": "Heat", "@pipe": "MainHeat"}, {"@pipeClass": "Fuel", "@pipe": "QuantumFuel"}]}, "ControllerDef": {"@controllableTags": "quantum_drive"}}}, {"@name": "hardpoint_quantum_interdiction_generator", "@class": "ItemPort", "ItemPort": {"@minsize": "1", "@maxsize": "1", "@flags": "invisible uneditable", "Types": {"Type": {"@type": "QuantumInterdictionGenerator", "@subtypes": ""}}, "Connections": {"Connection": [{"@pipeClass": "Power", "@pipe": "MainPower", "@prio_Manageable": "1"}, {"@pipeClass": "Heat", "@pipe": "MainHeat"}]}}}, {"@name": "hardpoint_quantum_fuel_tank", "@class": "ItemPort", "ItemPort": {"@minsize": "1", "@maxsize": "1", "@flags": "invisible uneditable", "Types": {"Type": {"@type": "QuantumFuelTank", "@subtypes": "QuantumFuel"}}, "Connections": {"Connection": {"@pipeClass": "Output", "@pipe": "QuantumFuel"}}}}, {"@name": "hardpoint_radar", "@class": "ItemPort", "ItemPort": {"@minsize": "2", "@maxsize": "2", "@flags": "invisible uneditable", "Types": {"Type": {"@type": "Radar", "@subtypes": "ShortRangeRadar,MidRangeRadar"}}, "ControllerDef": {"@controllableTags": "pilotSeat"}, "Connections": {"Connection": [{"@pipeClass": "Power", "@pipe": "MainPower"}, {"@pipeClass": "Heat", "@pipe": "MainHeat"}]}}}, {"@name": "hardpoint_scanner", "@class": "ItemPort", "ItemPort": {"@minsize": "1", "@maxsize": "1", "@flags": "invisible uneditable", "Types": {"Type": {"@type": "Scanner"}}, "Connections": {"Connection": [{"@pipeClass": "Power", "@pipe": "MainPower"}, {"@pipeClass": "Heat", "@pipe": "MainHeat"}]}}}, {"@name": "hardpoint_ping", "@class": "ItemPort", "ItemPort": {"@minsize": "1", "@maxsize": "1", "@flags": "invisible uneditable", "Types": {"Type": {"@type": "Ping"}}, "Connections": {"Connection": [{"@pipeClass": "Power", "@pipe": "MainPower"}, {"@pipeClass": "Heat", "@pipe": "MainHeat"}]}}}, {"@name": "hardpoint_transponder", "@class": "ItemPort", "ItemPort": {"@minsize": "1", "@maxsize": "1", "@flags": "invisible uneditable", "Types": {"Type": {"@type": "Transponder"}}, "Connections": {"Connection": [{"@pipeClass": "Power", "@pipe": "MainPower"}, {"@pipeClass": "Heat", "@pipe": "MainHeat"}]}}}, {"@name": "hardpoint_Right_Body_Weapon", "@class": "ItemPort", "ItemPort": {"@minsize": "3", "@maxsize": "3", "@flags": "", "@display_name": "port_NameWeaponSlot02", "@defaultWeaponGroup": "2", "Types": {"Type": [{"@type": "Turret", "@subtypes": "GunTurret"}, {"@type": "WeaponGun", "@subtypes": "Gun"}]}, "Pitch": {"@min": "-30", "@max": "5"}, "Yaw": {"@min": "-15", "@max": "15"}, "Connections": {"Connection": [{"@pipeClass": "Power", "@pipe": "MainPower"}, {"@pipeClass": "Heat", "@pipe": "MainHeat"}]}}}, {"@name": "hardpoint_Left_Body_Weapon", "@class": "ItemPort", "ItemPort": {"@minsize": "3", "@maxsize": "3", "@flags": "", "@display_name": "port_NameWeaponSlot02", "@defaultWeaponGroup": "2", "Types": {"Type": [{"@type": "Turret", "@subtypes": "GunTurret"}, {"@type": "WeaponGun", "@subtypes": "Gun"}]}, "Pitch": {"@min": "-30", "@max": "5"}, "Yaw": {"@min": "-15", "@max": "15"}, "Connections": {"Connection": [{"@pipeClass": "Power", "@pipe": "MainPower"}, {"@pipeClass": "Heat", "@pipe": "MainHeat"}]}}}, {"@name": "hardpoint_fuel_intake_left", "@class": "ItemPort", "ItemPort": {"@minsize": "1", "@maxsize": "1", "@flags": "invisible uneditable", "Types": {"Type": {"@type": "FuelIntake"}}, "Connections": {"Connection": [{"@pipeClass": "Power", "@pipe": "MainPower"}, {"@pipeClass": "Heat", "@pipe": "MainHeat"}, {"@pipeClass": "Fuel", "@pipe": "IntakeFuel"}]}}}, {"@name": "hardpoint_seat_pilot", "@class": "ItemPort", "ItemPort": {"@minsize": "1", "@maxsize": "1", "@flags": "uneditable ", "Types": {"Type": {"@type": "Seat"}}, "Connections": {"Connection": [{"@pipeClass": "Power", "@pipe": "MainPower"}, {"@pipeClass": "Heat", "@pipe": "MainHeat"}]}, "ControllerDef": {"@controllableTags": "pilotSeat", "UserDef": {"Observerables": {"Observerable": [{"@itemType": "FlightController", "@screensDefault": "Screen_Flight_HUD, Screen_Left_Upper", "@screensAvail": "Screen_Flight_HUD, VS_Left0, Screen_Left_Outer, Screen_Left_Lower, Screen_Right_Lower, Screen_Right_Outer, Screen_Left_Upper, Screen_Right_Upper"}, {"@itemType": "Seat", "@screensDefault": "VS_Right0, Screen_Right_Upper", "@screensAvail": "VS_Right0, Screen_Left_Outer, Screen_Left_Lower, Screen_Right_Lower, Screen_Right_Outer, Screen_Left_Upper, Screen_Right_Upper"}, {"@itemType": "QuantumDrive", "@screensDefault": "", "@screensAvail": "Screen_Flight_HUD"}, {"@itemType": "Radar", "@screensDefault": "Screen_Radar", "@screensAvail": "Screen_Radar"}, {"@itemType": "EnergyController", "@screensDefault": "Screen_Left_Lower", "@screensAvail": "Screen_Left_Outer, Screen_Left_Lower, Screen_Right_Lower, Screen_Right_Outer, Screen_Left_Upper, Screen_Right_Upper"}, {"@itemType": "ShieldController", "@screensDefault": "Screen_Right_Lower", "@screensAvail": "Screen_Left_Outer, Screen_Left_Lower, Screen_Right_Lower, Screen_Right_Outer, Screen_Left_Upper, Screen_Right_Upper"}, {"@itemType": "CoolerController", "@screensDefault": "Screen_Left_Outer", "@screensAvail": "Screen_Left_Outer, Screen_Left_Lower, Screen_Right_Lower, Screen_Right_Outer, Screen_Left_Upper, Screen_Right_Upper"}, {"@itemType": "WeaponController", "@screensDefault": "Screen_Right_Outer", "@screensAvail": "Screen_Left_Outer, Screen_Left_Lower, Screen_Right_Lower, Screen_Right_Outer, Screen_Left_Upper, Screen_Right_Upper"}, {"@itemType": "CommsController", "@screensDefault": "", "@screensAvail": "Screen_Left_Outer, Screen_Left_Lower, Screen_Right_Lower, Screen_Right_Outer, Screen_Left_Upper, Screen_Right_Upper"}]}, "PriorityGroups": {"PriorityGroup": [{"@itemType": "EnergyController", "tags": {"@tag": "energy_controller", "Priority": {"@value": "1"}}}, {"@itemType": "CoolerController", "@defaultPriority": "50"}, {"@itemType": "CommsController", "@defaultPriority": "50"}, {"@itemType": "ShieldController", "@defaultPriority": "50"}, {"@itemType": "WeaponController", "@defaultPriority": "100"}, {"@itemType": "FlightController"}, {"@itemType": "QuantumDrive", "@defaultPriority": "observe_only"}, {"@itemType": "LightController"}, {"@itemType": "LandingSystem"}, {"@itemType": "Avionics"}, {"@itemType": "QuantumFuelTank"}, {"@itemType": "MultiLight"}, {"@itemType": "Radar", "@defaultPriority": "no_control", "tags": {"@tag": "pilotSeat", "Priority": {"@value": "exclusive_control"}}}, {"@itemType": "SelfDestruct"}, {"@itemType": "DoorController"}, {"@itemType": "QuantumDrive", "@defaultPriority": "observe_only"}, {"@itemType": "QuantumInterdictionGenerator"}, {"@itemType": "Scanner"}, {"@itemType": "Ping"}, {"@itemType": "Seat", "@defaultPriority": "no_control", "tags": {"@tag": "pilotSeat", "Priority": {"@value": "exclusive_control"}}}]}}, "UsableDef": {"PriorityGroups": {"PriorityGroup": [{"@itemType": "SeatDashboard", "@defaultPriority": "no_control", "tags": {"@tag": "PilotDashBoard", "Priority": {"@value": "exclusive_control"}}}, {"@itemType": "Seat", "@defaultPriority": "no_control", "tags": {"@tag": "pilotSeat", "Priority": {"@value": "exclusive_control"}}}]}}}}}, {"@name": "hardpoint_copilot_seat", "@class": "ItemPort", "ItemPort": {"@minsize": "1", "@maxsize": "1", "@flags": "uneditable ", "Types": {"Type": {"@type": "Seat"}}, "ControllerDef": [{"@controllableTags": "copilotSeat", "UserDef": {"Observerables": {"Observerable": [{"@itemType": "Radar", "@screensDefault": "Screen_Radar", "@screensAvail": "Screen_Radar"}, {"@itemType": "EnergyController", "@screensDefault": "Screen_Left_Upper", "@screensAvail": "Screen_Left_Upper, Screen_Right_Upper, Screen_Left_Lower, Screen_Right_Lower"}, {"@itemType": "ShieldController", "@screensDefault": "Screen_Right_Upper", "@screensAvail": "Screen_Left_Upper, Screen_Right_Upper, Screen_Left_Lower, Screen_Right_Lower"}, {"@itemType": "CoolerController", "@screensDefault": "Screen_Left_Lower", "@screensAvail": "Screen_Left_Upper, Screen_Right_Upper, Screen_Left_Lower, Screen_Right_Lower"}, {"@itemType": "WeaponController", "@screensDefault": "Screen_Right_Lower", "@screensAvail": "Screen_Left_Upper, Screen_Right_Upper, Screen_Left_Lower, Screen_Right_Lower"}, {"@itemType": "CommsController", "@screensDefault": "", "@screensAvail": "Screen_Left_Upper, Screen_Right_Upper, Screen_Left_Lower, Screen_Right_Lower"}]}, "PriorityGroups": {"PriorityGroup": [{"@itemType": "EnergyController", "@defaultPriority": "observe_only"}, {"@itemType": "CommsController", "@defaultPriority": "100"}, {"@itemType": "CoolerController", "@defaultPriority": "100"}, {"@itemType": "ShieldController", "@defaultPriority": "100"}, {"@itemType": "WeaponController", "@defaultPriority": "50"}, {"@itemType": "FlightController", "@defaultPriority": "observe_only"}, {"@itemType": "QuantumDrive", "@defaultPriority": "observe_only"}, {"@itemType": "LandingSystem", "@defaultPriority": "observe_only"}, {"@itemType": "Avionics", "@defaultPriority": "observe_only"}, {"@itemType": "QuantumFuelTank", "@defaultPriority": "observe_only"}, {"@itemType": "MultiLight", "@defaultPriority": "observe_only"}, {"@itemType": "Radar", "@defaultPriority": "no_control", "tags": {"@tag": "copilotSeat", "Priority": {"@value": "exclusive_control"}}}, {"@itemType": "SelfDestruct", "@defaultPriority": "observe_only"}, {"@itemType": "DoorController", "@defaultPriority": "observe_only"}, {"@itemType": "QuantumDrive", "@defaultPriority": "observe_only"}, {"@itemType": "LightController", "@defaultPriority": "observe_only"}, {"@itemType": "Seat", "@defaultPriority": "no_control", "tags": {"@tag": "copilotSeat", "Priority": {"@value": "exclusive_control"}}}]}}, "UsableDef": {"PriorityGroups": {"PriorityGroup": [{"@itemType": "SeatDashboard", "@defaultPriority": "no_control", "tags": {"@tag": "CoPilotDashBoard", "Priority": {"@value": "exclusive_control"}}}, {"@itemType": "Seat", "@defaultPriority": "no_control", "tags": {"@tag": "copilotSeat", "Priority": {"@value": "exclusive_control"}}}]}}}, {"@controllableTags": "coPilotSeat"}], "Connections": {"Connection": [{"@pipeClass": "Power", "@pipe": "MainPower"}, {"@pipeClass": "Heat", "@pipe": "MainHeat"}]}}}, {"@name": "Wing_Left", "@class": "AnimatedJoint", "@damagemax": "880", "@detachRatio": "1", "@detachBaseForce": "0,-10,0", "@detachRandomForce": "0.5, -0.5, 0.5", "@detachRandomRotation": "0.5,0,0.3", "@detachProbability": "1", "@id": "modPart_wingleft", "Effects": {"DetachFx": [{"@joint": "Wing_Left", "@squibPhysical": "40", "@squibEnergy": "40", "@squibRadius": "1", "@pos_offset": "1.75202,-0.657829,1.04794", "@rot_offset": "0.0,1.0,0.0", "@helperID": "Wing_Left_SQUIB_1m001", "@effect": ""}, {"@joint": "Wing_Left", "@squibPhysical": "40", "@squibEnergy": "40", "@squibRadius": "1", "@pos_offset": "3.78102,3.52808,1.04794", "@rot_offset": "0.0,1.0,0.0", "@helperID": "Wing_Left_SQUIB_1m002", "@effect": ""}, {"@joint": "Wing_Left", "@squibPhysical": "40", "@squibEnergy": "40", "@squibRadius": ".5", "@pos_offset": "2.91509,1.32483,1.04794", "@rot_offset": "0.0,1.0,0.0", "@helperID": "Wing_Left_SQUIB_.5m002", "@effect": ""}, {"@joint": "Wing_Left", "@partName": "Body", "@effect": "Damage/LT_Damage/LT_Fire_FX.LT_Fire.lt_fire_4m_loop_fixed", "@pos_offset": "3.35163,-0.0111121,1.02874", "@rot_offset": "-0.5,0.866026,0.0", "@helperID": "Wing_Left_PFX_DetachFX_lt_fire_4m_loop_fixed004"}, {"@joint": "Wing_Left", "@effect": "Damage/LT_Damage/LT_Fire_FX.LT_Fire.lt_fire_4m_loop_fixed", "@pos_offset": "1.93033,1.87439,1.02874", "@rot_offset": "0.965926,-0.258819,0.0", "@helperID": "Wing_Left_PFX_DebrisFX_lt_fire_4m_loop_fixed006"}, {"@joint": "Wing_Left", "@partName": "Body", "@effect": "Damage/LT_Damage/LT_Fire_FX.LT_Fire.lt_fire_4m_loop_fixed", "@pos_offset": "3.8533,1.45577,1.04853", "@rot_offset": "-0.965926,0.258819,0.0", "@helperID": "Wing_Left_PFX_DetachFX_lt_fire_4m_loop_fixed006"}, {"@joint": "Wing_Left", "@partName": "Body", "@effect": "Damage/LT_Damage/LT_Fire_FX.LT_Fire.lt_fire_50cm_loop_fixed", "@pos_offset": "2.66193,1.61926,1.43497", "@rot_offset": "-0.707107,0.707107,0.0", "@helperID": "Wing_Left_PFX_DetachFX_lt_fire_50cm_loop_fixed003"}, {"@joint": "Wing_Left", "@partName": "Body", "@effect": "Damage/LT_Damage/LT_Fire_FX.LT_Fire.lt_fire_50cm_loop_fixed", "@pos_offset": "3.71641,2.76685,0.2545", "@rot_offset": "-0.730103,0.212654,-0.649405", "@helperID": "Wing_Left_PFX_DetachFX_lt_fire_50cm_loop_fixed004"}, {"@joint": "Wing_Left", "@partName": "Body", "@effect": "Damage/LT_Damage/LT_Smoke_FX.LT_Smoke.lt_smoke_1m_loop_trail", "@pos_offset": "3.13281,1.8073,0.389721", "@rot_offset": "-0.730103,0.0373298,-0.682316", "@helperID": "Wing_Left_PFX_DetachFX_lt_smoke_1m_loop_trail003"}, {"@joint": "Wing_Left", "@partName": "Body", "@effect": "Damage/LT_Damage/LT_Smoke_FX.LT_Smoke.lt_smoke_1m_loop_trail", "@pos_offset": "3.01294,3.13012,0.698513", "@rot_offset": "-0.395598,0.0997124,-0.912995", "@helperID": "Wing_Left_PFX_DetachFX_lt_smoke_1m_loop_trail004"}, {"@joint": "Wing_Left", "@partName": "Body", "@effect": "Damage/LT_Damage/LT_Smoke_FX.LT_Smoke.lt_smoke_2m_loop_trail", "@pos_offset": "2.97036,-0.508503,0.989561", "@rot_offset": "-0.996195,0.0871558,0.0", "@helperID": "Wing_Left_PFX_DetachFX_lt_smoke_2m_loop_trail004"}, {"@joint": "Wing_Left", "@partName": "Body", "@effect": "Damage/LT_Damage/LT_Sparks_FX.LT_Sparks.lt_sparks_1m_loop_fixed", "@pos_offset": "1.75189,0.0773346,0.451842", "@rot_offset": "-0.937631,0.264852,-0.225169", "@helperID": "Wing_Left_PFX_DetachFX_lt_sparks_1m_loop_fixed002"}, {"@joint": "Wing_Left", "@partName": "Body", "@effect": "Damage/LT_Damage/LT_Sparks_FX.LT_Sparks.lt_sparks_2m_loop_fixed", "@pos_offset": "2.66193,1.61926,1.43497", "@rot_offset": "-0.707107,0.707107,0.0", "@helperID": "Wing_Left_PFX_DetachFX_lt_sparks_2m_loop_fixed002"}, {"@joint": "Wing_Left", "@partName": "Body", "@effect": "Damage/LT_Damage/LT_Sparks_FX.LT_Sparks.lt_sparks_4m_once_fixed", "@pos_offset": "3.33293,1.68532,0.989561", "@rot_offset": "-0.965926,0.258819,0.0", "@helperID": "Wing_Left_PFX_DetachFX_lt_sparks_4m_once_fixed002"}, {"@joint": "Wing_Left", "@effect": "Damage/LT_Damage/LT_Fire_FX.LT_Fire.lt_fire_4m_loop_fixed", "@pos_offset": "1.61842,1.51007,0.811815", "@rot_offset": "0.906308,-0.422618,0.0", "@helperID": "Wing_Left_PFX_DebrisFX_lt_fire_4m_loop_fixed007"}, {"@joint": "Wing_Left", "@effect": "Damage/LT_Damage/LT_Smoke_FX.LT_Smoke.lt_smoke_2m_loop_trail", "@pos_offset": "2.12917,-0.100482,0.989561", "@rot_offset": "0.819152,-0.573577,0.0", "@helperID": "Wing_Left_PFX_DebrisFX_lt_smoke_2m_loop_trail005"}, {"@joint": "Wing_Left", "@effect": "Damage/LT_Damage/LT_Smoke_FX.LT_Smoke.lt_smoke_2m_loop_trail", "@pos_offset": "3.11159,2.52999,0.989561", "@rot_offset": "0.5,-0.866025,0.0", "@helperID": "Wing_Left_PFX_DebrisFX_lt_smoke_2m_loop_trail006"}, {"@joint": "Wing_Left", "@effect": "Damage/LT_Damage/LT_Smoke_FX.LT_Smoke.lt_smoke_4m_linger_loop_trail", "@pos_offset": "0.992034,1.90313,0.746554", "@rot_offset": "0.707107,-0.707107,0.0", "@helperID": "Wing_Left_PFX_DebrisFX_lt_smoke_4m_linger_loop_trail003"}, {"@joint": "Wing_Left", "@partName": "Body", "@effect": "Damage/LT_Damage/LT_Smoke_FX.LT_Smoke.lt_smoke_2m_loop_trail", "@pos_offset": "3.76565,2.03679,0.989561", "@rot_offset": "-0.906308,-0.422618,0.0", "@helperID": "Wing_Left_PFX_DetachFX_lt_smoke_2m_loop_trail002"}, {"@joint": "Wing_Left", "@partName": "Body", "@effect": "Damage/LT_Damage/LT_Explode_FX.LT_Explode.lt_explode_2m_once_fixed", "@pos_offset": "1.93033,1.87439,1.02874", "@rot_offset": "0.965926,-0.258819,0.0", "@helperID": "Wing_Left_PFX_DetachFX_lt_explode_2m_once_fixed002"}]}, "Parts": {"Part": [{"@name": "hardpoint_Man_Thruster_Left_Wing_Top", "@class": "ItemPort", "ItemPort": {"@minsize": "1", "@maxsize": "1", "@flags": "uneditable", "@display_name": "port_NameThrustManoeuv03", "Types": {"Type": {"@type": "ManneuverThruster", "@subtypes": ""}}, "Connections": {"Connection": [{"@pipeClass": "Power", "@pipe": "MainPower"}, {"@pipeClass": "Heat", "@pipe": "MainHeat"}, {"@pipeClass": "Fuel", "@pipe": "MainFuel"}]}}}, {"@name": "hardpoint_Left_Wing_Utility", "@class": "ItemPort", "ItemPort": {"@minsize": "1", "@maxsize": "1", "@flags": "uneditable", "@display_name": "port_NameWeaponSlot02", "Pitch": {"@min": "-30", "@max": "5"}, "Yaw": {"@min": "-15", "@max": "15"}, "Connections": {"Connection": [{"@pipeClass": "Power", "@pipe": "MainPower"}, {"@pipeClass": "Heat", "@pipe": "MainHeat"}]}}}, {"@name": "hardpoint_Left_Wing_Weapon", "@class": "ItemPort", "ItemPort": {"@minsize": "3", "@maxsize": "3", "@flags": "", "@display_name": "port_NameWeaponSlot02", "@defaultWeaponGroup": "1", "Types": {"Type": [{"@type": "Turret", "@subtypes": "GunTurret"}, {"@type": "WeaponGun", "@subtypes": "Gun"}]}, "Pitch": {"@min": "-30", "@max": "5"}, "Yaw": {"@min": "-15", "@max": "15"}, "Connections": {"Connection": [{"@pipeClass": "Power", "@pipe": "MainPower"}, {"@pipeClass": "Heat", "@pipe": "MainHeat"}]}}}, {"@name": "hardpoint_Man_Thruster_Left_Outer_Bot", "@class": "ItemPort", "ItemPort": {"@minsize": "1", "@maxsize": "1", "@flags": "uneditable", "@display_name": "port_NameThrustManoeuv03", "Types": {"Type": {"@type": "ManneuverThruster", "@subtypes": ""}}, "Connections": {"Connection": [{"@pipeClass": "Power", "@pipe": "MainPower"}, {"@pipeClass": "Heat", "@pipe": "MainHeat"}, {"@pipeClass": "Fuel", "@pipe": "MainFuel"}]}}}, {"@name": "hardpoint_Man_Thruster_Left_Outer_Top", "@class": "ItemPort", "ItemPort": {"@minsize": "1", "@maxsize": "1", "@flags": "uneditable", "@display_name": "port_NameThrustManoeuv03", "Types": {"Type": {"@type": "ManneuverThruster", "@subtypes": ""}}, "Connections": {"Connection": [{"@pipeClass": "Power", "@pipe": "MainPower"}, {"@pipeClass": "Heat", "@pipe": "MainHeat"}, {"@pipeClass": "Fuel", "@pipe": "MainFuel"}]}}}, {"@name": "hardpoint_Man_Thruster_Left_Wing_Bot", "@class": "ItemPort", "ItemPort": {"@minsize": "1", "@maxsize": "1", "@flags": "uneditable", "@display_name": "port_NameThrustManoeuv03", "Types": {"Type": {"@type": "ManneuverThruster", "@subtypes": ""}}, "Connections": {"Connection": [{"@pipeClass": "Power", "@pipe": "MainPower"}, {"@pipeClass": "Heat", "@pipe": "MainHeat"}, {"@pipeClass": "Fuel", "@pipe": "MainFuel"}]}}}]}}, {"@name": "hardpoint_seat_access", "@class": "ItemPort", "ItemPort": {"@minsize": "1", "@maxsize": "4", "@flags": "", "Types": {"Type": {"@type": "SeatAccess"}}, "Connections": {"Connection": [{"@pipeClass": "Power", "@pipe": "MainPower"}, {"@pipeClass": "Heat", "@pipe": "MainHeat"}]}}}, {"@name": "hardpoint_cooler_right", "@class": "ItemPort", "ItemPort": {"@minsize": "2", "@maxsize": "2", "@flags": "invisible", "Types": {"Type": {"@type": "Cooler", "@subtypes": ""}}, "Connections": {"Connection": [{"@pipeClass": "Power", "@pipe": "MainPower"}, {"@pipeClass": "Heat", "@pipe": "MainHeat"}]}}}, {"@name": "hardpoint_shield_generator_right", "@class": "ItemPort", "ItemPort": {"@minsize": "2", "@maxsize": "2", "@flags": "invisible", "@display_name": "port_NameShieldGen", "Types": {"Type": {"@type": "Shield", "@subtypes": ""}}, "Connections": {"Connection": [{"@pipeClass": "Power", "@pipe": "MainPower"}, {"@pipeClass": "Heat", "@pipe": "MainHeat"}, {"@pipeClass": "Shield", "@pipe": "Shield"}]}}}, {"@name": "hardpoint_controller_weapon", "@class": "ItemPort", "ItemPort": {"@minsize": "1", "@maxsize": "1", "@flags": "invisible uneditable", "Types": {"Type": {"@type": "WeaponController"}}, "Connections": {"Connection": [{"@pipeClass": "Power", "@pipe": "MainPower"}, {"@pipeClass": "Heat", "@pipe": "MainHeat"}]}, "ControllerDef": {"UsableDef": {"PriorityGroups": {"PriorityGroup": [{"@itemType": "Turret"}, {"@itemType": "WeaponGun"}, {"@itemType": "WeaponDefensive"}, {"@itemType": "MissileLauncher"}, {"@itemType": "Missile"}]}}}}}, {"@name": "hardpoint_controller_flight", "@class": "ItemPort", "ItemPort": {"@minsize": "1", "@maxsize": "1", "@flags": "invisible uneditable", "Types": {"Type": {"@type": "FlightController"}}, "Connections": {"Connection": [{"@pipeClass": "Power", "@pipe": "MainPower"}, {"@pipeClass": "Heat", "@pipe": "MainHeat"}, {"@pipeClass": "Fuel", "@pipe": "MainFuel"}]}, "ControllerDef": {"UsableDef": {"PriorityGroups": {"PriorityGroup": [{"@itemType": "MainThruster", "@defaultPriority": "exclusive_control"}, {"@itemType": "ManneuverThruster", "@defaultPriority": "exclusive_control"}, {"@itemType": "QuantumDrive", "@defaultPriority": "exclusive_control"}]}}}}}, {"@name": "hardpoint_controller_shield", "@class": "ItemPort", "ItemPort": {"@minsize": "1", "@maxsize": "1", "@flags": "invisible uneditable", "Types": {"Type": {"@type": "ShieldController"}}, "Connections": {"Connection": [{"@pipeClass": "Power", "@pipe": "MainPower"}, {"@pipeClass": "Heat", "@pipe": "MainHeat"}, {"@pipeClass": "Shield", "@pipe": "Shield"}]}, "ControllerDef": {"UsableDef": {"PriorityGroups": {"PriorityGroup": {"@itemType": "Shield"}}}}}}, {"@name": "hardpoint_controller_cooler", "@class": "ItemPort", "ItemPort": {"@minsize": "1", "@maxsize": "1", "@flags": "invisible uneditable", "Types": {"Type": {"@type": "CoolerController"}}, "ControllerDef": {"UsableDef": {"PriorityGroups": {"PriorityGroup": [{"@itemType": "Cooler"}, {"@itemType": "HeatSink"}]}}}}}, {"@name": "hardpoint_heat_sink", "@class": "ItemPort", "ItemPort": {"@minsize": "1", "@maxsize": "1", "@flags": "invisible uneditable", "Types": {"Type": {"@type": "HeatSink"}}, "Connections": {"Connection": [{"@pipeClass": "Input", "@pipe": "MainHeat"}, {"@pipeClass": "Output", "@pipe": "MainHeat"}]}}}, {"@name": "hardpoint_controller_energy", "@class": "ItemPort", "ItemPort": {"@minsize": "1", "@maxsize": "1", "@flags": "invisible uneditable", "Types": {"Type": {"@type": "EnergyController"}}, "Connections": {"Connection": [{"@pipeClass": "Power", "@pipe": "MainPower"}, {"@pipeClass": "Heat", "@pipe": "MainHeat"}]}, "ControllerDef": {"@controllableTags": "energy_controller", "UsableDef": {"PriorityGroups": {"PriorityGroup": [{"@itemType": "PowerPlant", "@defaultPriority": "exclusive_control"}, {"@itemType": "FuelIntake", "@defaultPriority": "exclusive_control"}, {"@itemType": "FuelTank", "@defaultPriority": "exclusive_control"}]}}}}}, {"@name": "hardpoint_cargogrid_rear", "@class": "ItemPort", "ItemPort": {"@minsize": "1", "@maxsize": "1", "@flags": "selfphys uneditable", "Types": {"Type": {"@type": "Cargo", "@subtypes": ""}}}}, {"@name": "hardpoint_cargogrid_main", "@class": "ItemPort", "ItemPort": {"@minsize": "1", "@maxsize": "1", "@flags": "selfphys uneditable", "Types": {"Type": {"@type": "Cargo", "@subtypes": ""}}}}, {"@name": "DRAK_Cutlass_Black_Int_Cockpit", "@class": "ItemPort", "ItemPort": {"@minsize": "1", "@maxsize": "1", "@flags": "uneditable", "Types": {"Type": {"@type": "Room", "@subtypes": ""}}}, "Parts": {"Part": [{"@name": "hardpoint_turret", "@class": "ItemPort", "ItemPort": {"@minsize": "1", "@maxsize": "6", "@flags": "$uneditable lower", "@display_name": "port_NameTurret02", "@displayTop": "1", "Types": {"Type": {"@type": "TurretBase", "@subtypes": "MannedTurret"}}, "Pitch": {"@min": "-45", "@max": "85"}, "Yaw": {"@min": "-180", "@max": "180"}, "Connections": {"Connection": [{"@pipeClass": "Power", "@pipe": "MainPower"}, {"@pipeClass": "Heat", "@pipe": "MainHeat"}]}, "ControllerDef": {"@controllableTags": "UpperTurret", "UserDef": {"Observerables": {"Observerable": [{"@itemType": "FlightController", "@screensDefault": "Screen_Left_Top", "@screensAvail": "Screen_Left_Top, Screen_Left_Bottom, Screen_Right_Top, Screen_Right_Bottom"}, {"@itemType": "TurretBase", "@componentTag": "Engine.Components.SCItemTargetSelectorComponent", "@screensDefault": "Screen_Right_Top", "@screensAvail": "Screen_Left_Top, Screen_Left_Bottom, Screen_Right_Top, Screen_Right_Bottom"}, {"@itemType": "Radar", "@screensDefault": "Screen_Radar", "@screensAvail": "Screen_Radar"}, {"@itemType": "TurretBase", "@componentTag": "Engine.Components.SCItemSeat", "@screensDefault": "Screen_Turret_HUD, Screen_Left_Bottom", "@screensAvail": "Screen_Turret_HUD, Screen_Left_Top, Screen_Left_Bottom, Screen_Right_Top, Screen_Right_Bottom"}, {"@itemType": "EnergyController", "@screensDefault": "", "@screensAvail": "Screen_Left_Top, Screen_Left_Bottom, Screen_Right_Top, Screen_Right_Bottom"}, {"@itemType": "ShieldController", "@screensDefault": "", "@screensAvail": "Screen_Left_Top, Screen_Left_Bottom, Screen_Right_Top, Screen_Right_Bottom"}, {"@itemType": "CoolerController", "@screensDefault": "", "@screensAvail": "Screen_Left_Top, Screen_Left_Bottom, Screen_Right_Top, Screen_Right_Bottom"}, {"@itemType": "WeaponController", "@screensDefault": "", "@screensAvail": "Screen_Left_Top, Screen_Left_Bottom, Screen_Right_Top, Screen_Right_Bottom"}, {"@itemType": "CommsController", "@screensDefault": "Screen_Right_Bottom", "@screensAvail": "Screen_Left_Top, Screen_Left_Bottom, Screen_Right_Top, Screen_Right_Bottom"}]}, "PriorityGroups": {"PriorityGroup": [{"@itemType": "TurretBase", "@defaultPriority": "no_control", "tags": {"@tag": "UpperTurret", "Priority": {"@value": "exclusive_control"}}}, {"@itemType": "EnergyController", "@defaultPriority": "observe_only"}, {"@itemType": "CoolerController", "@defaultPriority": "observe_only"}, {"@itemType": "ShieldController", "@defaultPriority": "observe_only"}, {"@itemType": "FlightController", "@defaultPriority": "observe_only"}, {"@itemType": "Radar", "@defaultPriority": "no_control", "tags": {"@tag": "UpperTurret", "Priority": {"@value": "exclusive_control"}}}, {"@itemType": "TargetSelector", "@defaultPriority": "observe_only"}, {"@itemType": "CommsController", "@defaultPriority": "observe_only"}]}}, "UsableDef": {"PriorityGroups": {"PriorityGroup": [{"@itemType": "TurretBase", "@defaultPriority": "no_control", "tags": {"@tag": "UpperTurret", "Priority": {"@value": "exclusive_control"}}}, {"@itemType": "WeaponGun", "@defaultPriority": "no_control", "tags": {"@tag": "UpperTurret", "Priority": {"@value": "exclusive_control"}}}]}}}}}, {"@name": "hardpoint_radar_turret", "@class": "ItemPort", "ItemPort": {"@minsize": "2", "@maxsize": "2", "@flags": "invisible uneditable", "Types": {"Type": {"@type": "Radar", "@subtypes": "ShortRangeRadar,MidRangeRadar"}}, "ControllerDef": {"@controllableTags": "UpperTurret"}, "Connections": {"Connection": [{"@pipeClass": "Power", "@pipe": "MainPower"}, {"@pipeClass": "Heat", "@pipe": "MainHeat"}]}}}]}}, {"@name": "DRAK_Cutlass_Black_Int_Rear", "@class": "ItemPort", "ItemPort": {"@minsize": "1", "@maxsize": "1", "@flags": "uneditable", "Types": {"Type": {"@type": "Room", "@subtypes": ""}}}}, {"@name": "hardpoint_controller_door", "@class": "ItemPort", "ItemPort": {"@minsize": "1", "@maxsize": "1", "@flags": "invisible uneditable", "Types": {"Type": {"@type": "DoorController"}}, "ControllerDef": {"UsableDef": {"PriorityGroups": {"PriorityGroup": [{"@itemType": "Door", "@defaultPriority": "exclusive_control"}, {"@itemType": "SeatAccess", "@defaultPriority": "exclusive_control"}]}}}}}, {"@name": "DRAK_Cutlass_Canopy_Variants", "@class": "AnimatedJoint", "Parts": {"Part": {"@name": "DRAK_Cutlass_Canopy_Attach", "@class": "Animated", "Animated": {"@filename": "Objects/Spaceships/Ships/DRAK/Cutlass/DRAK_Cutlass_Black_Canopy.cga", "@material": "", "@id": "modNoseVariantGeo"}, "Parts": {"Part": {"@name": "Canopy", "@class": "AnimatedJoint", "@damageMax": "3000", "@detachRatio": "0", "@detachBaseForce": "0,5,-1", "@detachRandomForce": "0.5, 0.5, 0.5", "@detachRandomRotation": "0.5,0,0.3", "@detachProbability": "1", "DamageBehaviors": {"DamageBehavior": [{"@class": "DetachPart", "@damageRatioMin": "1", "DetachPart": {"Part": [{"@name": "Thruster_Main_Left", "@Probability": "0.3"}, {"@name": "Thruster_Main_Right", "@Probability": "0.3"}, {"@name": "Missile_Housing_Left", "@Probability": "0.2"}, {"@name": "Missile_Housing_Right", "@Probability": "0.2"}, {"@name": "Wing_Left", "@Probability": "0.5"}, {"@name": "Wing_Right", "@Probability": "0.5"}, {"@name": "Sidedoor_Left", "@Probability": "0.2"}, {"@name": "Sidedoor_Left_02", "@Probability": "0.2"}, {"@name": "Sidedoor_Right", "@Probability": "0.2"}, {"@name": "Sidedoor_Right_02", "@Probability": "0.2"}, {"@name": "Tail", "@Probability": "1"}, {"@name": "Body", "@Probability": "1"}]}}, {"@class": "Group", "@damageRatioMin": "1", "Group": {"@name": "Destroy"}}]}}}}}}, {"@name": "hardpoint_bed_lower", "@class": "ItemPort", "ItemPort": {"@minsize": "1", "@maxsize": "1", "@flags": "uneditable", "@display_name": "port_NameBed", "Types": {"Type": {"@type": "Usable"}}, "ControllerDef": {"@controllableTags": "lowerBed", "UserDef": {"Observerables": null, "PriorityGroups": {"PriorityGroup": {"@itemType": "Usable", "@defaultPriority": "no_control", "tags": {"@tag": "lowerBed", "Priority": {"@value": "exclusive_control"}}}}}, "UsableDef": {"PriorityGroups": {"PriorityGroup": {"@itemType": "Usable", "@defaultPriority": "no_control", "tags": {"@tag": "lowerBed", "Priority": {"@value": "exclusive_control"}}}}}}}}, {"@name": "hardpoint_bed_upper", "@class": "ItemPort", "ItemPort": {"@minsize": "1", "@maxsize": "1", "@flags": "uneditable", "@display_name": "port_NameBed", "Types": {"Type": {"@type": "Usable"}}, "ControllerDef": {"@controllableTags": "upperBed", "UserDef": {"Observerables": null, "PriorityGroups": {"PriorityGroup": {"@itemType": "Usable", "@defaultPriority": "no_control", "tags": {"@tag": "upperBed", "Priority": {"@value": "exclusive_control"}}}}}, "UsableDef": {"PriorityGroups": {"PriorityGroup": {"@itemType": "Usable", "@defaultPriority": "no_control", "tags": {"@tag": "upperBed", "Priority": {"@value": "exclusive_control"}}}}}}}}, {"@name": "hardpoint_radar_copilot", "@class": "ItemPort", "ItemPort": {"@minsize": "2", "@maxsize": "2", "@flags": "invisible uneditable", "Types": {"Type": {"@type": "Radar", "@subtypes": "ShortRangeRadar,MidRangeRadar"}}, "ControllerDef": {"@controllableTags": "copilotSeat"}, "Connections": {"Connection": [{"@pipeClass": "Power", "@pipe": "MainPower"}, {"@pipeClass": "Heat", "@pipe": "MainHeat"}]}}}, {"@name": "hardpoint_self_destruct_pilot", "@class": "ItemPort", "ItemPort": {"@minsize": "1", "@maxsize": "1", "@flags": "invisible uneditable", "Types": {"Type": {"@type": "SelfDestruct"}}, "Connections": {"Connection": {"@pipeClass": "Power", "@pipe": "MainPower"}}}}, {"@name": "hardpoint_controller_comms", "@class": "ItemPort", "ItemPort": {"@minsize": "1", "@maxsize": "1", "@flags": "invisible uneditable", "Types": {"Type": {"@type": "CommsController"}}, "ControllerDef": {"UsableDef": {"PriorityGroups": {"PriorityGroup": {"@itemType": "Comms"}}}}}}, {"@name": "hardpoint_controller_light", "@class": "ItemPort", "ItemPort": {"@minsize": "1", "@maxsize": "1", "@flags": "invisible uneditable", "Types": {"Type": {"@type": "LightController"}}, "Connections": {"Connection": [{"@pipeClass": "Power", "@pipe": "MainPower"}, {"@pipeClass": "Heat", "@pipe": "MainHeat"}, {"@pipeClass": "Fuel", "@pipe": "MainFuel"}]}, "ControllerDef": {"UsableDef": {"PriorityGroups": {"PriorityGroup": {"@itemType": "Light"}}}}}}]}}, {"@name": "landingpad_helper", "@class": "ItemPort", "ItemPort": {"@minsize": "1", "@maxsize": "1", "@flags": "uneditable", "@display_name": "Landing System", "Types": {"Type": {"@type": "LandingSystem"}}}}, {"@name": "hardpoint_lights_ext", "@class": "ItemPort", "ItemPort": {"@minSize": "1", "@maxsize": "1", "@flags": "uneditable", "Connections": {"Connection": {"@pipeClass": "Power", "@pipe": "MainPower"}}}}, {"@name": "Tail", "@class": "AnimatedJoint", "@damagemax": "3600", "@detachRatio": "0", "@detachBaseForce": "0,-10,1", "@detachRandomForce": "0.5, -0.5, 0.5", "@detachRandomRotation": "0.5,0,0.3", "@detachProbability": "1", "@id": "modPart_tail", "Effects": {"DetachFx": [{"@joint": "Tail", "@squibPhysical": "40", "@squibEnergy": "40", "@squibRadius": "3", "@pos_offset": "-2.0544,9.16439,1.83974", "@rot_offset": "0.0,-1.0,0.0", "@helperID": "Tail_SQUIB_3m001", "@effect": ""}, {"@joint": "Tail", "@effect": "Damage/LT_Damage/LT_Fire_FX.LT_Fire.lt_fire_16m_loop_fixed", "@pos_offset": "-0.0876244,8.57249,-0.36421", "@rot_offset": "0.0,0.999368,-0.0355466", "@helperID": "Tail_PFX_DebrisFX_lt_fire_16m_loop_fixed007"}, {"@joint": "Tail", "@effect": "Damage/LT_Damage/LT_Smoke_FX.LT_Smoke.lt_smoke_8m_loop_trail", "@pos_offset": "-0.0876239,0.605332,-0.543782", "@rot_offset": "0.0,0.999994,-0.00339421", "@helperID": "Tail_PFX_DebrisFX_lt_smoke_8m_loop_trail001"}, {"@joint": "Tail", "@effect": "Damage/LT_Damage/LT_Explode_FX.LT_Explode.lt_explode_4m_once_fixed", "@pos_offset": "-0.0876244,10.1081,-0.36421", "@rot_offset": "0.0,-1.0,0.0", "@helperID": "Tail_PFX_DebrisFX_lt_explode_4m_once_fixed"}, {"@joint": "Tail", "@squibPhysical": "40", "@squibEnergy": "40", "@squibRadius": "3", "@pos_offset": "-4.76524,9.16439,1.01289", "@rot_offset": "0.0,-1.0,0.0", "@helperID": "Tail_SQUIB_3m002", "@effect": ""}, {"@joint": "Tail", "@squibPhysical": "40", "@squibEnergy": "40", "@squibRadius": "3", "@pos_offset": "-4.76524,9.16439,-2.91136", "@rot_offset": "0.0,-1.0,0.0", "@helperID": "Tail_SQUIB_3m003", "@effect": ""}, {"@joint": "Tail", "@squibPhysical": "40", "@squibEnergy": "40", "@squibRadius": "3", "@pos_offset": "0.672743,9.16439,-3.25305", "@rot_offset": "0.0,-1.0,0.0", "@helperID": "Tail_SQUIB_3m004", "@effect": ""}, {"@joint": "Tail", "@squibPhysical": "40", "@squibEnergy": "40", "@squibRadius": "3", "@pos_offset": "4.76171,9.16439,-2.59524", "@rot_offset": "0.0,-1.0,0.0", "@helperID": "Tail_SQUIB_3m005", "@effect": ""}, {"@joint": "Tail", "@squibPhysical": "40", "@squibEnergy": "40", "@squibRadius": "3", "@pos_offset": "3.23721,9.16439,1.33417", "@rot_offset": "0.0,-1.0,0.0", "@helperID": "Tail_SQUIB_3m006", "@effect": ""}]}, "DamageBehaviors": {"DamageBehavior": [{"@class": "DetachPart", "@damageRatioMin": "1", "DetachPart": {"Part": [{"@name": "Thruster_Main_Left", "@Probability": "0.2"}, {"@name": "Thruster_Main_Right", "@Probability": "0.2"}, {"@name": "Missile_Housing_Left", "@Probability": "0.2"}, {"@name": "Missile_Housing_Right", "@Probability": "0.2"}, {"@name": "Body", "@Probability": "1"}, {"@name": "Tail", "@Probability": "1"}]}}, {"@class": "Group", "@damageRatioMin": "1", "Group": {"@name": "Destroy"}}]}, "Parts": {"Part": [{"@name": "Missile_Housing_Left", "@class": "AnimatedJoint", "@damagemax": "640", "@detachRatio": "1", "@detachBaseForce": "0,0,1", "@detachRandomForce": "0.5, 0.5, 0.5", "@detachRandomRotation": "0.5,0,0.3", "@detachProbability": "1", "Effects": {"DetachFx": [{"@joint": "Missile_Housing_Left", "@squibPhysical": "40", "@squibEnergy": "40", "@squibRadius": "1", "@pos_offset": "0.691968,0.366921,-0.294505", "@rot_offset": "0.0,1.0,0.0", "@helperID": "Missile_Housing_Left_SQUIB_1m005", "@effect": ""}, {"@joint": "Missile_Housing_Left", "@effect": "Damage/LT_Damage/LT_Fire_FX.LT_Fire.lt_fire_2m_loop_fixed", "@pos_offset": "0.143245,0.331919,-0.0101511", "@rot_offset": "0.422618,0.0,-0.906308", "@helperID": "Missile_Housing_Left_PFX_DebrisFX_lt_fire_2m_loop_fixed005"}, {"@joint": "Missile_Housing_Left", "@partName": "Tail", "@effect": "Damage/LT_Damage/LT_Fire_FX.LT_Fire.lt_fire_2m_loop_fixed", "@pos_offset": "0.143245,0.331919,-0.737578", "@rot_offset": "0.0,0.0,1.0", "@helperID": "Missile_Housing_Left_PFX_DetachFX_lt_fire_2m_loop_fixed006"}, {"@joint": "Missile_Housing_Left", "@effect": "Damage/LT_Damage/LT_Smoke_FX.LT_Smoke.lt_smoke_2m_loop_trail", "@pos_offset": "0.654703,-0.386597,-0.179584", "@rot_offset": "0.0,0.0,-1.0", "@helperID": "Missile_Housing_Left_PFX_DebrisFX_lt_smoke_2m_loop_trail001"}, {"@joint": "Missile_Housing_Left", "@partName": "Tail", "@effect": "Damage/LT_Damage/LT_Sparks_FX.LT_Sparks.lt_sparks_2m_loop_fixed", "@pos_offset": "0.863644,0.331919,-0.737578", "@rot_offset": "0.0,0.0,1.0", "@helperID": "Missile_Housing_Left_PFX_DetachFX_lt_sparks_2m_loop_fixed001"}, {"@joint": "Missile_Housing_Left", "@partName": "Tail", "@effect": "Damage/LT_Damage/LT_Sparks_FX.LT_Sparks.lt_sparks_2m_loop_fixed", "@pos_offset": "1.56176,-0.341121,-0.179584", "@rot_offset": "-0.906308,0.0,0.422618", "@helperID": "Missile_Housing_Left_PFX_DetachFX_lt_sparks_2m_loop_fixed002"}]}, "Parts": {"Part": [{"@name": "hardpoint_Left_Pylon_01", "@class": "ItemPort", "ItemPort": {"@minsize": "4", "@maxsize": "4", "@flags": "left", "@display_name": "port_NameWeaponSlot04", "@displayPos": "275,260", "@displayTop": "1", "Types": {"Type": {"@type": "MissileLauncher", "@subtypes": "MissileRack"}}, "Connections": {"Connection": [{"@pipeClass": "Power", "@pipe": "MainPower"}, {"@pipeClass": "Heat", "@pipe": "MainHeat"}]}}}, {"@name": "hardpoint_Left_Pylon_02", "@class": "ItemPort", "ItemPort": {"@minsize": "4", "@maxsize": "4", "@flags": "left", "@display_name": "port_NameWeaponSlot04", "@displayPos": "275,260", "@displayTop": "1", "Types": {"Type": {"@type": "MissileLauncher", "@subtypes": "MissileRack"}}, "Connections": {"Connection": [{"@pipeClass": "Power", "@pipe": "MainPower"}, {"@pipeClass": "Heat", "@pipe": "MainHeat"}]}}}, {"@name": "hardpoint_Left_Pylon_03", "@class": "ItemPort", "ItemPort": {"@minsize": "4", "@maxsize": "4", "@flags": "left", "@display_name": "port_NameWeaponSlot04", "@displayPos": "275,260", "@displayTop": "1", "Types": {"Type": {"@type": "MissileLauncher", "@subtypes": "MissileRack"}}, "Connections": {"Connection": [{"@pipeClass": "Power", "@pipe": "MainPower"}, {"@pipeClass": "Heat", "@pipe": "MainHeat"}]}}}]}}, {"@name": "Missile_Housing_Right", "@class": "AnimatedJoint", "@damagemax": "640", "@detachRatio": "1", "@detachBaseForce": "0,0,1", "@detachRandomForce": "0.5, 0.5, 0.5", "@detachRandomRotation": "0.5,0,0.3", "@detachProbability": "1", "Effects": {"DetachFx": [{"@joint": "Missile_Housing_Right", "@squibPhysical": "40", "@squibEnergy": "40", "@squibRadius": "1", "@pos_offset": "0.354316,-0.20634,-0.257883", "@rot_offset": "0.0,1.0,0.0", "@helperID": "Missile_Housing_Right_SQUIB_1m006", "@effect": ""}, {"@joint": "Missile_Housing_Right", "@effect": "Damage/LT_Damage/LT_Fire_FX.LT_Fire.lt_fire_2m_loop_fixed", "@pos_offset": "0.0657559,0.331919,-0.00169281", "@rot_offset": "0.0,0.0,-1.0", "@helperID": "Missile_Housing_Right_PFX_DebrisFX_lt_fire_2m_loop_fixed006"}, {"@joint": "Missile_Housing_Right", "@partName": "Tail", "@effect": "Damage/LT_Damage/LT_Fire_FX.LT_Fire.lt_fire_2m_loop_fixed", "@pos_offset": "0.571619,0.331917,-0.73758", "@rot_offset": "0.309976,-0.422618,0.851651", "@helperID": "Missile_Housing_Right_PFX_DetachFX_lt_fire_2m_loop_fixed007"}, {"@joint": "Missile_Housing_Right", "@partName": "Tail", "@effect": "Damage/LT_Damage/LT_Smoke_FX.LT_Smoke.lt_smoke_2m_loop_trail", "@pos_offset": "-0.0121542,-0.133547,-0.81788", "@rot_offset": "0.34202,0.0,0.939693", "@helperID": "Missile_Housing_Right_PFX_DetachFX_lt_smoke_2m_loop_trail001"}, {"@joint": "Missile_Housing_Right", "@effect": "Damage/LT_Damage/LT_Smoke_FX.LT_Smoke.lt_smoke_1m_loop_trail", "@pos_offset": "0.37783,-0.511401,-0.0549295", "@rot_offset": "0.0,0.0,-1.0", "@helperID": "Missile_Housing_Right_PFX_DebrisFX_lt_smoke_1m_loop_trail003"}, {"@joint": "Missile_Housing_Right", "@partName": "Tail", "@effect": "Damage/LT_Damage/LT_Sparks_FX.LT_Sparks.lt_sparks_2m_loop_fixed", "@pos_offset": "0.911065,-0.33852,-0.81788", "@rot_offset": "0.0,0.34202,0.939693", "@helperID": "Missile_Housing_Right_PFX_DetachFX_lt_sparks_2m_loop_fixed001"}, {"@joint": "Missile_Housing_Right", "@partName": "Tail", "@effect": "Damage/LT_Damage/LT_Sparks_FX.LT_Sparks.lt_sparks_2m_loop_fixed", "@pos_offset": "-0.472312,-0.33852,-0.81788", "@rot_offset": "0.34202,0.0,0.939693", "@helperID": "Missile_Housing_Right_PFX_DetachFX_lt_sparks_2m_loop_fixed006"}, {"@joint": "Missile_Housing_Right", "@partName": "Tail", "@effect": "Damage/LT_Damage/LT_Sparks_FX.LT_Sparks.lt_sparks_2m_loop_fixed", "@pos_offset": "0.911065,-1.5823,-0.81788", "@rot_offset": "-0.148839,-0.175907,0.97309", "@helperID": "Missile_Housing_Right_PFX_DetachFX_lt_sparks_2m_loop_fixed007"}]}, "Parts": {"Part": [{"@name": "hardpoint_Right_Pylon_01", "@class": "ItemPort", "ItemPort": {"@minsize": "4", "@maxsize": "4", "@flags": "left", "@display_name": "port_NameWeaponSlot04", "@displayPos": "275,260", "@displayTop": "1", "Types": {"Type": {"@type": "MissileLauncher", "@subtypes": "MissileRack"}}, "Connections": {"Connection": [{"@pipeClass": "Power", "@pipe": "MainPower"}, {"@pipeClass": "Heat", "@pipe": "MainHeat"}]}}}, {"@name": "hardpoint_Right_Pylon_02", "@class": "ItemPort", "ItemPort": {"@minsize": "4", "@maxsize": "4", "@flags": "left", "@display_name": "port_NameWeaponSlot04", "@displayPos": "275,260", "@displayTop": "1", "Types": {"Type": {"@type": "MissileLauncher", "@subtypes": "MissileRack"}}, "Connections": {"Connection": [{"@pipeClass": "Power", "@pipe": "MainPower"}, {"@pipeClass": "Heat", "@pipe": "MainHeat"}]}}}, {"@name": "hardpoint_Right_Pylon_03", "@class": "ItemPort", "ItemPort": {"@minsize": "4", "@maxsize": "4", "@flags": "left", "@display_name": "port_NameWeaponSlot04", "@displayPos": "275,260", "@displayTop": "1", "Types": {"Type": {"@type": "MissileLauncher", "@subtypes": "MissileRack"}}, "Connections": {"Connection": [{"@pipeClass": "Power", "@pipe": "MainPower"}, {"@pipeClass": "Heat", "@pipe": "MainHeat"}]}}}]}}, {"@name": "hardpoint_Man_Thruster_Right_Tail", "@class": "ItemPort", "ItemPort": {"@minsize": "1", "@maxsize": "1", "@flags": "uneditable", "@display_name": "port_NameThrustManoeuv03", "Types": {"Type": {"@type": "ManneuverThruster", "@subtypes": ""}}, "Connections": {"Connection": [{"@pipeClass": "Power", "@pipe": "MainPower"}, {"@pipeClass": "Heat", "@pipe": "MainHeat"}, {"@pipeClass": "Fuel", "@pipe": "MainFuel"}]}}}, {"@name": "hardpoint_Man_Thruster_Left_Tail", "@class": "ItemPort", "ItemPort": {"@minsize": "1", "@maxsize": "1", "@flags": "uneditable", "@display_name": "port_NameThrustManoeuv03", "Types": {"Type": {"@type": "ManneuverThruster", "@subtypes": ""}}, "Connections": {"Connection": [{"@pipeClass": "Power", "@pipe": "MainPower"}, {"@pipeClass": "Heat", "@pipe": "MainHeat"}, {"@pipeClass": "Fuel", "@pipe": "MainFuel"}]}}}, {"@name": "hardpoint_Tail_Utility", "@class": "ItemPort", "ItemPort": {"@minsize": "1", "@maxsize": "1", "@flags": "uneditable", "@display_name": "port_NameWeaponSlot02", "Pitch": {"@min": "-30", "@max": "5"}, "Yaw": {"@min": "-15", "@max": "15"}, "Connections": {"Connection": [{"@pipeClass": "Power", "@pipe": "MainPower"}, {"@pipeClass": "Heat", "@pipe": "MainHeat"}]}}}, {"@name": "Thruster_Main_Base_Right", "@class": "AnimatedJoint", "@damagemax": "480", "Parts": {"Part": [{"@name": "hardpoint_Man_Thruster_Right_Rear_Top", "@class": "ItemPort", "ItemPort": {"@minsize": "1", "@maxsize": "1", "@flags": "uneditable", "@display_name": "port_NameThrustManoeuv03", "Types": {"Type": {"@type": "ManneuverThruster", "@subtypes": ""}}, "Connections": {"Connection": [{"@pipeClass": "Power", "@pipe": "MainPower"}, {"@pipeClass": "Heat", "@pipe": "MainHeat"}, {"@pipeClass": "Fuel", "@pipe": "MainFuel"}]}}}, {"@name": "hardpoint_Man_Thruster_Right_Rear_Bot", "@class": "ItemPort", "ItemPort": {"@minsize": "1", "@maxsize": "1", "@flags": "uneditable", "@display_name": "port_NameThrustManoeuv03", "Types": {"Type": {"@type": "ManneuverThruster", "@subtypes": ""}}, "Connections": {"Connection": [{"@pipeClass": "Power", "@pipe": "MainPower"}, {"@pipeClass": "Heat", "@pipe": "MainHeat"}, {"@pipeClass": "Fuel", "@pipe": "MainFuel"}]}}}, {"@name": "hardpoint_Man_Thruster_Right_Front_Top", "@class": "ItemPort", "ItemPort": {"@minsize": "1", "@maxsize": "1", "@flags": "uneditable", "@display_name": "port_NameThrustManoeuv03", "Types": {"Type": {"@type": "ManneuverThruster", "@subtypes": ""}}, "Connections": {"Connection": [{"@pipeClass": "Power", "@pipe": "MainPower"}, {"@pipeClass": "Heat", "@pipe": "MainHeat"}, {"@pipeClass": "Fuel", "@pipe": "MainFuel"}]}}}, {"@name": "hardpoint_Man_Thruster_Right_Front_Bot", "@class": "ItemPort", "ItemPort": {"@minsize": "1", "@maxsize": "1", "@flags": "uneditable", "@display_name": "port_NameThrustManoeuv03", "Types": {"Type": {"@type": "ManneuverThruster", "@subtypes": ""}}, "Connections": {"Connection": [{"@pipeClass": "Power", "@pipe": "MainPower"}, {"@pipeClass": "Heat", "@pipe": "MainHeat"}, {"@pipeClass": "Fuel", "@pipe": "MainFuel"}]}}}, {"@name": "Thruster_Main_Right", "@class": "AnimatedJoint", "@damagemax": "1200", "@detachRatio": "1", "@detachBaseForce": "5,0,0", "@detachRandomForce": "0.5, 0.5, 0.5", "@detachRandomRotation": "0.5,0,0.3", "@detachProbability": "1", "Effects": {"DetachFx": [{"@joint": "Thruster_Main_Right", "@squibPhysical": "40", "@squibEnergy": "40", "@squibRadius": "1", "@pos_offset": "-2.34654,-0.0872437,-0.142281", "@rot_offset": "0.0,1.0,0.0", "@helperID": "Thruster_Main_Right_SQUIB_1m003", "@effect": ""}, {"@joint": "Thruster_Main_Right", "@partName": "Thruster_Main_Base_Right", "@effect": "Damage/LT_Damage/LT_Fire_FX.LT_Fire.lt_fire_4m_loop_fixed", "@pos_offset": "-4.04615,0.0580383,-0.0924207", "@rot_offset": "1.0,0.0,0.0", "@helperID": "Thruster_Main_Right_PFX_DetachFX_lt_fire_4m_loop_fixed002"}, {"@joint": "Thruster_Main_Right", "@effect": "Damage/LT_Damage/LT_Fire_FX.LT_Fire.lt_fire_4m_loop_fixed", "@pos_offset": "-1.39968,0.019812,-0.05395", "@rot_offset": "-0.984808,-0.173648,0.0", "@helperID": "Thruster_Main_Right_PFX_DebrisFX_lt_fire_4m_loop_fixed010"}, {"@joint": "Thruster_Main_Right", "@effect": "Damage/LT_Damage/LT_Smoke_FX.LT_Smoke.lt_smoke_2m_loop_trail", "@pos_offset": "-1.46242,0.199839,0.123796", "@rot_offset": "-0.996195,-0.0871557,0.0", "@helperID": "Thruster_Main_Right_PFX_DebrisFX_lt_smoke_2m_loop_trail010"}, {"@joint": "Thruster_Main_Right", "@partName": "Thruster_Main_Base_Right", "@effect": "Damage/LT_Damage/LT_Fire_FX.LT_Fire.lt_fire_1m_loop_fixed", "@pos_offset": "-2.14282,-0.329471,0.0642743", "@rot_offset": "0.918974,-0.39325,0.0290163", "@helperID": "Thruster_Main_Right_PFX_DetachFX_lt_fire_1m_loop_fixed006"}, {"@joint": "Thruster_Main_Right", "@partName": "Thruster_Main_Base_Right", "@effect": "Damage/LT_Damage/LT_Fire_FX.LT_Fire.lt_fire_50cm_loop_fixed", "@pos_offset": "-2.53528,0.080918,0.547055", "@rot_offset": "0.342769,-0.69086,0.63657", "@helperID": "Thruster_Main_Right_PFX_DetachFX_lt_fire_50cm_loop_fixed007"}, {"@joint": "Thruster_Main_Right", "@partName": "Thruster_Main_Base_Right", "@effect": "Damage/LT_Damage/LT_Fire_FX.LT_Fire.lt_fire_50cm_loop_fixed", "@pos_offset": "-1.99685,0.246171,0.0150748", "@rot_offset": "0.867715,0.431414,-0.246887", "@helperID": "Thruster_Main_Right_PFX_DetachFX_lt_fire_50cm_loop_fixed008"}, {"@joint": "Thruster_Main_Right", "@partName": "Thruster_Main_Base_Right", "@effect": "Damage/LT_Damage/LT_Smoke_FX.LT_Smoke.lt_smoke_1m_loop_trail", "@pos_offset": "-1.98424,0.234653,0.010406", "@rot_offset": "0.834564,0.492459,-0.246957", "@helperID": "Thruster_Main_Right_PFX_DetachFX_lt_smoke_1m_loop_trail007"}, {"@joint": "Thruster_Main_Right", "@partName": "Thruster_Main_Base_Right", "@effect": "Damage/LT_Damage/LT_Smoke_FX.LT_Smoke.lt_smoke_1m_loop_trail", "@pos_offset": "-2.54052,0.0598804,-0.236102", "@rot_offset": "0.842184,-0.149388,0.518083", "@helperID": "Thruster_Main_Right_PFX_DetachFX_lt_smoke_1m_loop_trail008"}, {"@joint": "Thruster_Main_Right", "@partName": "Thruster_Main_Base_Right", "@effect": "Damage/LT_Damage/LT_Smoke_FX.LT_Smoke.lt_smoke_2m_loop_trail", "@pos_offset": "-3.72166,-0.00704224,0.123797", "@rot_offset": "0.996195,-0.0871557,0.0", "@helperID": "Thruster_Main_Right_PFX_DetachFX_lt_smoke_2m_loop_trail006"}, {"@joint": "Thruster_Main_Right", "@partName": "Thruster_Main_Base_Right", "@effect": "Damage/LT_Damage/LT_Smoke_FX.LT_Smoke.lt_smoke_2m_loop_trail", "@pos_offset": "-2.85363,-0.0871619,0.123796", "@rot_offset": "0.996195,-0.0871557,0.0", "@helperID": "Thruster_Main_Right_PFX_DetachFX_lt_smoke_2m_loop_trail007"}, {"@joint": "Thruster_Main_Right", "@partName": "Thruster_Main_Base_Right", "@effect": "Damage/LT_Damage/LT_Sparks_FX.LT_Sparks.lt_sparks_1m_loop_fixed", "@pos_offset": "-2.12281,-0.337754,0.0687511", "@rot_offset": "0.917374,-0.390518,0.0769442", "@helperID": "Thruster_Main_Right_PFX_DetachFX_lt_sparks_1m_loop_fixed004"}, {"@joint": "Thruster_Main_Right", "@partName": "Thruster_Main_Base_Right", "@effect": "Damage/LT_Damage/LT_Sparks_FX.LT_Sparks.lt_sparks_2m_loop_fixed", "@pos_offset": "-2.50833,0.0437549,0.574073", "@rot_offset": "-0.5,-0.707107,-0.5", "@helperID": "Thruster_Main_Right_PFX_DetachFX_lt_sparks_2m_loop_fixed004"}, {"@joint": "Thruster_Main_Right", "@partName": "Thruster_Main_Base_Right", "@effect": "Damage/LT_Damage/LT_Sparks_FX.LT_Sparks.lt_sparks_4m_once_fixed", "@pos_offset": "-2.62633,-0.138176,0.123796", "@rot_offset": "0.984808,-0.173648,0.0", "@helperID": "Thruster_Main_Right_PFX_DetachFX_lt_sparks_4m_once_fixed004"}, {"@joint": "Thruster_Main_Right", "@partName": "Thruster_Main_Base_Right", "@effect": "Damage/LT_Damage/LT_Fire_FX.LT_Fire.lt_fire_2m_loop_fixed", "@pos_offset": "-2.54214,0.0610645,-0.233696", "@rot_offset": "0.866025,0.0,0.5", "@helperID": "Thruster_Main_Right_PFX_DetachFX_lt_fire_2m_loop_fixed003"}, {"@joint": "Thruster_Main_Right", "@effect": "Damage/LT_Damage/LT_Smoke_FX.LT_Smoke.lt_smoke_1m_loop_trail", "@pos_offset": "-2.58627,0.0450171,0.0426801", "@rot_offset": "-0.993193,0.116438,0.00303887", "@helperID": "Thruster_Main_Right_PFX_DebrisFX_lt_smoke_1m_loop_trail009"}, {"@joint": "Thruster_Main_Right", "@partName": "Thruster_Main_Base_Right", "@effect": "Damage/LT_Damage/LT_Explode_FX.LT_Explode.lt_explode_2m_once_fixed", "@pos_offset": "-1.39968,0.019812,-0.05395", "@rot_offset": "-0.984808,-0.173648,0.0", "@helperID": "Thruster_Main_Right_PFX_DetachFX_lt_explode_2m_once_fixed002"}]}, "Parts": {"Part": [{"@name": "hardpoint_Main_Retro_Right", "@class": "ItemPort", "ItemPort": {"@minsize": "4", "@maxsize": "4", "@flags": "uneditable retro", "@requiredTags": "", "@display_name": "port_NameThrustMain01", "Types": {"Type": {"@type": "MainThruster", "@subtypes": ""}}, "Connections": {"Connection": [{"@pipeClass": "Power", "@pipe": "MainPower"}, {"@pipeClass": "Heat", "@pipe": "MainHeat"}, {"@pipeClass": "Fuel", "@pipe": "MainFuel"}]}}}, {"@name": "hardpoint_Main_Thruster_Right", "@class": "ItemPort", "ItemPort": {"@minsize": "4", "@maxsize": "4", "@flags": "uneditable", "@requiredTags": "", "@display_name": "port_NameThrustMain01", "Types": {"Type": {"@type": "MainThruster", "@subtypes": ""}}, "Connections": {"Connection": [{"@pipeClass": "Power", "@pipe": "MainPower"}, {"@pipeClass": "Heat", "@pipe": "MainHeat"}, {"@pipeClass": "Fuel", "@pipe": "MainFuel"}]}}}]}}, {"@name": "hardpoint_cm_launcher_right", "@class": "ItemPort", "ItemPort": {"@minsize": "2", "@maxsize": "2", "@flags": "left uneditable", "@display_name": "port_NameCountermeasure02", "Types": {"Type": {"@type": "WeaponDefensive", "@subtypes": "CountermeasureLauncher"}}, "Connections": {"Connection": [{"@pipeClass": "Power", "@pipe": "MainPower"}, {"@pipeClass": "Heat", "@pipe": "MainHeat"}]}}}]}}, {"@name": "Thruster_Main_Base_Left", "@class": "AnimatedJoint", "@damagemax": "480", "Parts": {"Part": [{"@name": "hardpoint_Man_Thruster_Left_Rear_Top", "@class": "ItemPort", "ItemPort": {"@minsize": "1", "@maxsize": "1", "@flags": "uneditable", "@display_name": "port_NameThrustManoeuv03", "Types": {"Type": {"@type": "ManneuverThruster", "@subtypes": ""}}, "Connections": {"Connection": [{"@pipeClass": "Power", "@pipe": "MainPower"}, {"@pipeClass": "Heat", "@pipe": "MainHeat"}, {"@pipeClass": "Fuel", "@pipe": "MainFuel"}]}}}, {"@name": "hardpoint_Man_Thruster_Left_Rear_Bot", "@class": "ItemPort", "ItemPort": {"@minsize": "1", "@maxsize": "1", "@flags": "uneditable", "@display_name": "port_NameThrustManoeuv03", "Types": {"Type": {"@type": "ManneuverThruster", "@subtypes": ""}}, "Connections": {"Connection": [{"@pipeClass": "Power", "@pipe": "MainPower"}, {"@pipeClass": "Heat", "@pipe": "MainHeat"}, {"@pipeClass": "Fuel", "@pipe": "MainFuel"}]}}}, {"@name": "hardpoint_Man_Thruster_Left_Front_Top", "@class": "ItemPort", "ItemPort": {"@minsize": "1", "@maxsize": "1", "@flags": "uneditable", "@display_name": "port_NameThrustManoeuv03", "Types": {"Type": {"@type": "ManneuverThruster", "@subtypes": ""}}, "Connections": {"Connection": [{"@pipeClass": "Power", "@pipe": "MainPower"}, {"@pipeClass": "Heat", "@pipe": "MainHeat"}, {"@pipeClass": "Fuel", "@pipe": "MainFuel"}]}}}, {"@name": "hardpoint_Man_Thruster_Left_Front_Bot", "@class": "ItemPort", "ItemPort": {"@minsize": "1", "@maxsize": "1", "@flags": "uneditable", "@display_name": "port_NameThrustManoeuv03", "Types": {"Type": {"@type": "ManneuverThruster", "@subtypes": ""}}, "Connections": {"Connection": [{"@pipeClass": "Power", "@pipe": "MainPower"}, {"@pipeClass": "Heat", "@pipe": "MainHeat"}, {"@pipeClass": "Fuel", "@pipe": "MainFuel"}]}}}, {"@name": "Thruster_Main_Left", "@class": "AnimatedJoint", "@damagemax": "1200", "@detachRatio": "1", "@detachBaseForce": "-5,0,0", "@detachRandomForce": "0.5, 0.5, 0.5", "@detachRandomRotation": "0.5,0,0.3", "@detachProbability": "1", "Effects": {"DetachFx": [{"@joint": "Thruster_Main_Left", "@squibPhysical": "40", "@squibEnergy": "40", "@squibRadius": "1", "@pos_offset": "2.42242,-0.0872424,-0.142276", "@rot_offset": "0.0,1.0,0.0", "@helperID": "Thruster_Main_Left_SQUIB_1m004", "@effect": ""}, {"@joint": "Thruster_Main_Left", "@partName": "Thruster_Main_Base_Left", "@effect": "Damage/LT_Damage/LT_Fire_FX.LT_Fire.lt_fire_4m_loop_fixed", "@pos_offset": "3.67284,0.0696704,-0.208905", "@rot_offset": "-1.0,0.0,0.0", "@helperID": "Thruster_Main_Left_PFX_DetachFX_lt_fire_4m_loop_fixed003"}, {"@joint": "Thruster_Main_Left", "@effect": "Damage/LT_Damage/LT_Fire_FX.LT_Fire.lt_fire_2m_loop_fixed", "@pos_offset": "1.83819,-0.14035,-0.208905", "@rot_offset": "1.0,0.0,0.0", "@helperID": "Thruster_Main_Left_PFX_DebrisFX_lt_fire_2m_loop_fixed004"}, {"@joint": "Thruster_Main_Left", "@partName": "Thruster_Main_Base_Left", "@effect": "Damage/LT_Damage/LT_Fire_FX.LT_Fire.lt_fire_4m_loop_fixed", "@pos_offset": "3.4926,-0.268022,0.240693", "@rot_offset": "-0.965926,0.258819,0.0", "@helperID": "Thruster_Main_Left_PFX_DetachFX_lt_fire_4m_loop_fixed008"}, {"@joint": "Thruster_Main_Left", "@partName": "Thruster_Main_Base_Left", "@effect": "Damage/LT_Damage/LT_Fire_FX.LT_Fire.lt_fire_50cm_loop_fixed", "@pos_offset": "2.31335,0.06948,0.579084", "@rot_offset": "-0.175444,-0.756178,0.630408", "@helperID": "Thruster_Main_Left_PFX_DetachFX_lt_fire_50cm_loop_fixed005"}, {"@joint": "Thruster_Main_Left", "@partName": "Thruster_Main_Base_Left", "@effect": "Damage/LT_Damage/LT_Fire_FX.LT_Fire.lt_fire_50cm_loop_fixed", "@pos_offset": "2.37549,0.0198975,-0.0731055", "@rot_offset": "-0.996195,-0.0871558,0.0", "@helperID": "Thruster_Main_Left_PFX_DetachFX_lt_fire_50cm_loop_fixed006"}, {"@joint": "Thruster_Main_Left", "@partName": "Thruster_Main_Base_Left", "@effect": "Damage/LT_Damage/LT_Smoke_FX.LT_Smoke.lt_smoke_1m_loop_trail", "@pos_offset": "2.3521,0.0327759,-0.241185", "@rot_offset": "-0.87813,-0.0634614,0.474195", "@helperID": "Thruster_Main_Left_PFX_DetachFX_lt_smoke_1m_loop_trail005"}, {"@joint": "Thruster_Main_Left", "@partName": "Thruster_Main_Base_Left", "@effect": "Damage/LT_Damage/LT_Sparks_FX.LT_Sparks.lt_sparks_1m_loop_fixed", "@pos_offset": "2.05889,-0.57724,-0.185178", "@rot_offset": "1.0,0.0,0.0", "@helperID": "Thruster_Main_Left_PFX_DetachFX_lt_sparks_1m_loop_fixed003"}, {"@joint": "Thruster_Main_Left", "@partName": "Thruster_Main_Base_Left", "@effect": "Damage/LT_Damage/LT_Sparks_FX.LT_Sparks.lt_sparks_2m_loop_fixed", "@pos_offset": "2.31093,-0.869448,0.154064", "@rot_offset": "-1.0,0.0,0.0", "@helperID": "Thruster_Main_Left_PFX_DetachFX_lt_sparks_2m_loop_fixed003"}, {"@joint": "Thruster_Main_Left", "@partName": "Thruster_Main_Base_Left", "@effect": "Damage/LT_Damage/LT_Sparks_FX.LT_Sparks.lt_sparks_4m_once_fixed", "@pos_offset": "2.97222,0.0832751,0.0752182", "@rot_offset": "-0.965926,0.258819,0.0", "@helperID": "Thruster_Main_Left_PFX_DetachFX_lt_sparks_4m_once_fixed003"}, {"@joint": "Thruster_Main_Left", "@effect": "Damage/LT_Damage/LT_Fire_FX.LT_Fire.lt_fire_4m_loop_fixed", "@pos_offset": "1.28108,-0.0295947,0.114393", "@rot_offset": "0.996195,0.0871557,0.0", "@helperID": "Thruster_Main_Left_PFX_DebrisFX_lt_fire_4m_loop_fixed007"}, {"@joint": "Thruster_Main_Left", "@effect": "Damage/LT_Damage/LT_Smoke_FX.LT_Smoke.lt_smoke_2m_loop_trail", "@pos_offset": "-0.698057,3.57296,-1.40639", "@rot_offset": "0.0,1.0,0.0", "@helperID": "Thruster_Main_Left_PFX_DebrisFX_lt_smoke_2m_loop_trail005"}, {"@joint": "Thruster_Main_Left", "@partName": "Thruster_Main_Base_Left", "@effect": "Damage/LT_Damage/LT_Smoke_FX.LT_Smoke.lt_smoke_2m_loop_trail", "@pos_offset": "3.40495,0.43475,0.0752181", "@rot_offset": "-0.906308,-0.422618,0.0", "@helperID": "Thruster_Main_Left_PFX_DetachFX_lt_smoke_2m_loop_trail003"}, {"@joint": "Thruster_Main_Left", "@effect": "Damage/LT_Damage/LT_Smoke_FX.LT_Smoke.lt_smoke_2m_loop_trail", "@pos_offset": "0.909994,-0.015271,-0.167788", "@rot_offset": "1.0,0.0,0.0", "@helperID": "Thruster_Main_Left_PFX_DebrisFX_lt_smoke_2m_loop_trail004"}, {"@joint": "Thruster_Main_Left", "@partName": "Thruster_Main_Base_Left", "@effect": "Damage/LT_Damage/LT_Smoke_FX.LT_Smoke.lt_smoke_2m_loop_trail", "@pos_offset": "4.58694,-0.0152722,-0.167788", "@rot_offset": "-1.0,0.0,0.0", "@helperID": "Thruster_Main_Left_PFX_DetachFX_lt_smoke_2m_loop_trail006"}, {"@joint": "Thruster_Main_Left", "@partName": "Thruster_Main_Base_Left", "@effect": "Damage/LT_Damage/LT_Sparks_FX.LT_Sparks.lt_sparks_2m_loop_fixed", "@pos_offset": "1.8386,0.245547,0.0112021", "@rot_offset": "-0.876911,0.425191,-0.224144", "@helperID": "Thruster_Main_Left_PFX_DetachFX_lt_sparks_2m_loop_fixed005"}, {"@joint": "Thruster_Main_Left", "@partName": "Thruster_Main_Base_Left", "@effect": "Damage/LT_Damage/LT_Sparks_FX.LT_Sparks.lt_sparks_1m_loop_fixed", "@pos_offset": "2.33627,-0.159747,-0.876119", "@rot_offset": "-1.0,0.0,0.0", "@helperID": "Thruster_Main_Left_PFX_DetachFX_lt_sparks_1m_loop_fixed001"}, {"@joint": "Thruster_Main_Left", "@partName": "Thruster_Main_Base_Left", "@effect": "Damage/LT_Damage/LT_Sparks_FX.LT_Sparks.lt_sparks_2m_loop_fixed", "@pos_offset": "1.96001,-0.325111,0.076254", "@rot_offset": "-0.939693,-0.34202,0.0", "@helperID": "Thruster_Main_Left_PFX_DetachFX_lt_sparks_2m_loop_fixed004"}, {"@joint": "Thruster_Main_Left", "@partName": "Thruster_Main_Base_Left", "@effect": "Damage/LT_Damage/LT_Explode_FX.LT_Explode.lt_explode_2m_once_fixed", "@pos_offset": "1.83819,-0.14035,-0.208905", "@rot_offset": "1.0,0.0,0.0", "@helperID": "Thruster_Main_Left_PFX_DetachFX_lt_explode_2m_once_fixed002"}]}, "Parts": {"Part": [{"@name": "hardpoint_Main_Retro_Left", "@class": "ItemPort", "ItemPort": {"@minsize": "4", "@maxsize": "4", "@flags": "uneditable retro", "@requiredTags": "", "@display_name": "port_NameThrustMain01", "Types": {"Type": {"@type": "MainThruster", "@subtypes": ""}}, "Connections": {"Connection": [{"@pipeClass": "Power", "@pipe": "MainPower"}, {"@pipeClass": "Heat", "@pipe": "MainHeat"}, {"@pipeClass": "Fuel", "@pipe": "MainFuel"}]}}}, {"@name": "hardpoint_Main_Thruster_Left", "@class": "ItemPort", "ItemPort": {"@minsize": "4", "@maxsize": "4", "@flags": "uneditable", "@requiredTags": "", "@display_name": "port_NameThrustMain01", "Types": {"Type": {"@type": "MainThruster", "@subtypes": ""}}, "Connections": {"Connection": [{"@pipeClass": "Power", "@pipe": "MainPower"}, {"@pipeClass": "Heat", "@pipe": "MainHeat"}, {"@pipeClass": "Fuel", "@pipe": "MainFuel"}]}}}]}}, {"@name": "hardpoint_cm_launcher_left", "@class": "ItemPort", "ItemPort": {"@minsize": "2", "@maxsize": "2", "@flags": "left uneditable", "@display_name": "port_NameCountermeasure02", "Types": {"Type": {"@type": "WeaponDefensive", "@subtypes": "CountermeasureLauncher"}}, "Connections": {"Connection": [{"@pipeClass": "Power", "@pipe": "MainPower"}, {"@pipeClass": "Heat", "@pipe": "MainHeat"}]}}}]}}, {"@name": "hardpoint_door_rear", "@class": "ItemPort", "ItemPort": {"@minsize": "1", "@maxsize": "1", "@flags": "uneditable", "Types": {"Type": {"@type": "Door"}}}}, {"@name": "hardpoint_door_left", "@class": "ItemPort", "ItemPort": {"@minsize": "1", "@maxsize": "1", "@flags": "uneditable", "Types": {"Type": {"@type": "Door"}}}}, {"@name": "hardpoint_door_right", "@class": "ItemPort", "ItemPort": {"@minsize": "1", "@maxsize": "1", "@flags": "uneditable", "Types": {"Type": {"@type": "Door"}}}}]}}]}}}}